{
"meta":{"test_sets":[],"test_metrics":[],"learn_metrics":[{"best_value":"Min","name":"RMSE"}],"launch_mode":"Train","parameters":"","iteration_count":1000,"learn_sets":["learn"],"name":"experiment"},
"iterations":[
{"learn":[32412.05129],"iteration":0,"passed_time":0.001511369769,"remaining_time":1.5098584},
{"learn":[30946.23148],"iteration":1,"passed_time":0.002975674727,"remaining_time":1.484861689},
{"learn":[29601.14737],"iteration":2,"passed_time":0.004515726744,"remaining_time":1.500726521},
{"learn":[28377.69462],"iteration":3,"passed_time":0.005857718234,"remaining_time":1.45857184},
{"learn":[27188.42368],"iteration":4,"passed_time":0.007224536987,"remaining_time":1.43768286},
{"learn":[26026.80062],"iteration":5,"passed_time":0.00868363273,"remaining_time":1.438588489},
{"learn":[24966.16499],"iteration":6,"passed_time":0.01054105283,"remaining_time":1.495323638},
{"learn":[23935.6823],"iteration":7,"passed_time":0.01269913595,"remaining_time":1.574692858},
{"learn":[22997.797],"iteration":8,"passed_time":0.0141569144,"remaining_time":1.558833575},
{"learn":[22095.77971],"iteration":9,"passed_time":0.01558501181,"remaining_time":1.542916169},
{"learn":[21244.60192],"iteration":10,"passed_time":0.01697634806,"remaining_time":1.526328021},
{"learn":[20453.77458],"iteration":11,"passed_time":0.01816262309,"remaining_time":1.495389301},
{"learn":[19724.42253],"iteration":12,"passed_time":0.01948552115,"remaining_time":1.479400721},
{"learn":[19007.80706],"iteration":13,"passed_time":0.0209484822,"remaining_time":1.475371675},
{"learn":[18371.79647],"iteration":14,"passed_time":0.02255688862,"remaining_time":1.481235686},
{"learn":[17742.02366],"iteration":15,"passed_time":0.02433324681,"remaining_time":1.496494679},
{"learn":[17186.69972],"iteration":16,"passed_time":0.02584619598,"remaining_time":1.494518274},
{"learn":[16652.99893],"iteration":17,"passed_time":0.02798900015,"remaining_time":1.526955452},
{"learn":[16143.65734],"iteration":18,"passed_time":0.02979026979,"remaining_time":1.538118667},
{"learn":[15669.05025],"iteration":19,"passed_time":0.03147135382,"remaining_time":1.542096337},
{"learn":[15257.6953],"iteration":20,"passed_time":0.03319576244,"remaining_time":1.54755483},
{"learn":[14843.04671],"iteration":21,"passed_time":0.03510244073,"remaining_time":1.560463047},
{"learn":[14457.97003],"iteration":22,"passed_time":0.03655262239,"remaining_time":1.552691829},
{"learn":[14120.35197],"iteration":23,"passed_time":0.03835953453,"remaining_time":1.559954404},
{"learn":[13801.53077],"iteration":24,"passed_time":0.03998975594,"remaining_time":1.559600482},
{"learn":[13522.21551],"iteration":25,"passed_time":0.04184502874,"remaining_time":1.567579153},
{"learn":[13239.65691],"iteration":26,"passed_time":0.04414508746,"remaining_time":1.590858152},
{"learn":[13003.04181],"iteration":27,"passed_time":0.04571052233,"remaining_time":1.586808132},
{"learn":[12772.62483],"iteration":28,"passed_time":0.04802993937,"remaining_time":1.608174867},
{"learn":[12557.48917],"iteration":29,"passed_time":0.04975114074,"remaining_time":1.608620217},
{"learn":[12355.34529],"iteration":30,"passed_time":0.05131134852,"remaining_time":1.603893443},
{"learn":[12178.68584],"iteration":31,"passed_time":0.0528924849,"remaining_time":1.599997668},
{"learn":[12014.02379],"iteration":32,"passed_time":0.05468473999,"remaining_time":1.602428593},
{"learn":[11867.36494],"iteration":33,"passed_time":0.05670800666,"remaining_time":1.611174542},
{"learn":[11725.85461],"iteration":34,"passed_time":0.05848436247,"remaining_time":1.612497422},
{"learn":[11593.31202],"iteration":35,"passed_time":0.06037902465,"remaining_time":1.616816105},
{"learn":[11481.08918],"iteration":36,"passed_time":0.06171346662,"remaining_time":1.606218064},
{"learn":[11377.3695],"iteration":37,"passed_time":0.06316941229,"remaining_time":1.599183543},
{"learn":[11274.52506],"iteration":38,"passed_time":0.06497855791,"remaining_time":1.601138311},
{"learn":[11188.72815],"iteration":39,"passed_time":0.06630751862,"remaining_time":1.591380447},
{"learn":[11103.12624],"iteration":40,"passed_time":0.06750647734,"remaining_time":1.57899297},
{"learn":[11028.90212],"iteration":41,"passed_time":0.068801821,"remaining_time":1.569336774},
{"learn":[10967.30235],"iteration":42,"passed_time":0.07062756129,"remaining_time":1.571873864},
{"learn":[10901.836],"iteration":43,"passed_time":0.07266308392,"remaining_time":1.578770642},
{"learn":[10846.62299],"iteration":44,"passed_time":0.07430413242,"remaining_time":1.57689881},
{"learn":[10796.52192],"iteration":45,"passed_time":0.07570317387,"remaining_time":1.570017997},
{"learn":[10748.094],"iteration":46,"passed_time":0.07749314186,"remaining_time":1.571297111},
{"learn":[10705.43246],"iteration":47,"passed_time":0.07945504806,"remaining_time":1.575858453},
{"learn":[10664.5742],"iteration":48,"passed_time":0.08097137884,"remaining_time":1.57150574},
{"learn":[10629.30857],"iteration":49,"passed_time":0.08235902531,"remaining_time":1.564821481},
{"learn":[10600.12565],"iteration":50,"passed_time":0.08378285511,"remaining_time":1.559018225},
{"learn":[10567.33401],"iteration":51,"passed_time":0.08548542411,"remaining_time":1.55846504},
{"learn":[10542.96643],"iteration":52,"passed_time":0.08834077025,"remaining_time":1.578466216},
{"learn":[10519.71849],"iteration":53,"passed_time":0.08997236655,"remaining_time":1.57618257},
{"learn":[10493.99816],"iteration":54,"passed_time":0.09127296748,"remaining_time":1.568235532},
{"learn":[10473.51434],"iteration":55,"passed_time":0.0925347787,"remaining_time":1.559871984},
{"learn":[10452.13651],"iteration":56,"passed_time":0.09373933741,"remaining_time":1.550810442},
{"learn":[10436.29025],"iteration":57,"passed_time":0.09493480095,"remaining_time":1.541872112},
{"learn":[10424.70138],"iteration":58,"passed_time":0.09621683545,"remaining_time":1.534576986},
{"learn":[10409.4042],"iteration":59,"passed_time":0.09772528072,"remaining_time":1.531029398},
{"learn":[10394.69139],"iteration":60,"passed_time":0.09894239246,"remaining_time":1.523064041},
{"learn":[10382.35995],"iteration":61,"passed_time":0.1006288414,"remaining_time":1.522416987},
{"learn":[10367.34155],"iteration":62,"passed_time":0.1026458691,"remaining_time":1.52665364},
{"learn":[10355.13484],"iteration":63,"passed_time":0.1044463698,"remaining_time":1.527528159},
{"learn":[10345.90858],"iteration":64,"passed_time":0.1060288454,"remaining_time":1.52518416},
{"learn":[10335.81072],"iteration":65,"passed_time":0.10736048,"remaining_time":1.519313459},
{"learn":[10324.56926],"iteration":66,"passed_time":0.1087573289,"remaining_time":1.514486385},
{"learn":[10314.06175],"iteration":67,"passed_time":0.1102321543,"remaining_time":1.510828938},
{"learn":[10303.78663],"iteration":68,"passed_time":0.1114097345,"remaining_time":1.503224099},
{"learn":[10296.76398],"iteration":69,"passed_time":0.1125568628,"remaining_time":1.49539832},
{"learn":[10289.44008],"iteration":70,"passed_time":0.1137415322,"remaining_time":1.488251879},
{"learn":[10283.24563],"iteration":71,"passed_time":0.1153507321,"remaining_time":1.486742769},
{"learn":[10276.72224],"iteration":72,"passed_time":0.1170521176,"remaining_time":1.486401548},
{"learn":[10270.90963],"iteration":73,"passed_time":0.1188737591,"remaining_time":1.487528391},
{"learn":[10266.84907],"iteration":74,"passed_time":0.1203698777,"remaining_time":1.484561825},
{"learn":[10261.62317],"iteration":75,"passed_time":0.1218656842,"remaining_time":1.48163016},
{"learn":[10256.41784],"iteration":76,"passed_time":0.1231981536,"remaining_time":1.476777867},
{"learn":[10250.91878],"iteration":77,"passed_time":0.124791922,"remaining_time":1.475104514},
{"learn":[10245.46422],"iteration":78,"passed_time":0.1261680031,"remaining_time":1.470895327},
{"learn":[10238.70028],"iteration":79,"passed_time":0.1274262763,"remaining_time":1.465402177},
{"learn":[10232.29566],"iteration":80,"passed_time":0.1286375926,"remaining_time":1.459480835},
{"learn":[10228.34975],"iteration":81,"passed_time":0.1298280749,"remaining_time":1.453441131},
{"learn":[10223.37393],"iteration":82,"passed_time":0.132090693,"remaining_time":1.459363439},
{"learn":[10218.14535],"iteration":83,"passed_time":0.1345407113,"remaining_time":1.467134423},
{"learn":[10214.44858],"iteration":84,"passed_time":0.1361807586,"remaining_time":1.465945813},
{"learn":[10210.96606],"iteration":85,"passed_time":0.1374785998,"remaining_time":1.46110977},
{"learn":[10206.43845],"iteration":86,"passed_time":0.1387951537,"remaining_time":1.45655144},
{"learn":[10202.14043],"iteration":87,"passed_time":0.140238231,"remaining_time":1.45337803},
{"learn":[10196.2352],"iteration":88,"passed_time":0.1419683945,"remaining_time":1.453182105},
{"learn":[10193.44027],"iteration":89,"passed_time":0.1433155229,"remaining_time":1.449079176},
{"learn":[10189.7001],"iteration":90,"passed_time":0.1445651782,"remaining_time":1.444063154},
{"learn":[10185.33274],"iteration":91,"passed_time":0.1461904236,"remaining_time":1.442835919},
{"learn":[10180.55486],"iteration":92,"passed_time":0.1480901135,"remaining_time":1.444276698},
{"learn":[10177.48865],"iteration":93,"passed_time":0.1500913054,"remaining_time":1.44662471},
{"learn":[10172.66814],"iteration":94,"passed_time":0.1515972956,"remaining_time":1.444163711},
{"learn":[10169.80307],"iteration":95,"passed_time":0.1530592475,"remaining_time":1.441307914},
{"learn":[10164.17495],"iteration":96,"passed_time":0.1544712657,"remaining_time":1.43801601},
{"learn":[10161.88123],"iteration":97,"passed_time":0.1560257441,"remaining_time":1.436073685},
{"learn":[10158.77573],"iteration":98,"passed_time":0.1573248319,"remaining_time":1.431814885},
{"learn":[10156.02987],"iteration":99,"passed_time":0.1585553529,"remaining_time":1.426998176},
{"learn":[10151.42883],"iteration":100,"passed_time":0.1597552711,"remaining_time":1.421980086},
{"learn":[10148.31231],"iteration":101,"passed_time":0.1614144996,"remaining_time":1.421080595},
{"learn":[10145.9109],"iteration":102,"passed_time":0.1645667817,"remaining_time":1.433168963},
{"learn":[10140.34827],"iteration":103,"passed_time":0.1676606575,"remaining_time":1.44446105},
{"learn":[10135.5861],"iteration":104,"passed_time":0.1692421903,"remaining_time":1.442588193},
{"learn":[10129.07409],"iteration":105,"passed_time":0.1707032915,"remaining_time":1.439705119},
{"learn":[10125.74615],"iteration":106,"passed_time":0.171890055,"remaining_time":1.434559058},
{"learn":[10124.28009],"iteration":107,"passed_time":0.1733292829,"remaining_time":1.431571485},
{"learn":[10120.43347],"iteration":108,"passed_time":0.1745588341,"remaining_time":1.42689836},
{"learn":[10118.48998],"iteration":109,"passed_time":0.1757186282,"remaining_time":1.421723447},
{"learn":[10116.94551],"iteration":110,"passed_time":0.1777503296,"remaining_time":1.423603991},
{"learn":[10111.51774],"iteration":111,"passed_time":0.1799542183,"remaining_time":1.426779873},
{"learn":[10108.68869],"iteration":112,"passed_time":0.1816242381,"remaining_time":1.425669904},
{"learn":[10108.30407],"iteration":113,"passed_time":0.1824686915,"remaining_time":1.418133866},
{"learn":[10103.64183],"iteration":114,"passed_time":0.1839620135,"remaining_time":1.415707669},
{"learn":[10101.03301],"iteration":115,"passed_time":0.185194187,"remaining_time":1.411307425},
{"learn":[10098.10768],"iteration":116,"passed_time":0.1865970203,"remaining_time":1.408249307},
{"learn":[10095.75363],"iteration":117,"passed_time":0.1879152432,"remaining_time":1.404586818},
{"learn":[10094.01475],"iteration":118,"passed_time":0.1891658803,"remaining_time":1.400463366},
{"learn":[10087.8294],"iteration":119,"passed_time":0.1907745262,"remaining_time":1.399013192},
{"learn":[10082.91405],"iteration":120,"passed_time":0.1931538112,"remaining_time":1.403158678},
{"learn":[10079.08787],"iteration":121,"passed_time":0.1951290032,"remaining_time":1.404289056},
{"learn":[10074.31386],"iteration":122,"passed_time":0.1969170574,"remaining_time":1.404034629},
{"learn":[10071.41958],"iteration":123,"passed_time":0.1985422912,"remaining_time":1.402605218},
{"learn":[10067.82677],"iteration":124,"passed_time":0.1998062195,"remaining_time":1.398643537},
{"learn":[10064.2802],"iteration":125,"passed_time":0.2010647496,"remaining_time":1.394687231},
{"learn":[10059.51476],"iteration":126,"passed_time":0.2024621338,"remaining_time":1.391727896},
{"learn":[10056.86256],"iteration":127,"passed_time":0.2036856569,"remaining_time":1.387608538},
{"learn":[10055.25809],"iteration":128,"passed_time":0.2048153292,"remaining_time":1.382900401},
{"learn":[10049.99584],"iteration":129,"passed_time":0.2059597454,"remaining_time":1.378345989},
{"learn":[10047.5859],"iteration":130,"passed_time":0.2076541545,"remaining_time":1.377492063},
{"learn":[10043.27671],"iteration":131,"passed_time":0.2099770854,"remaining_time":1.38075841},
{"learn":[10041.46156],"iteration":132,"passed_time":0.2119331192,"remaining_time":1.38154898},
{"learn":[10035.41494],"iteration":133,"passed_time":0.2133428963,"remaining_time":1.37876827},
{"learn":[10027.94105],"iteration":134,"passed_time":0.2148962917,"remaining_time":1.376928091},
{"learn":[10021.06839],"iteration":135,"passed_time":0.2164819066,"remaining_time":1.375296818},
{"learn":[10020.27554],"iteration":136,"passed_time":0.2173259612,"remaining_time":1.368994924},
{"learn":[10016.03726],"iteration":137,"passed_time":0.2185362768,"remaining_time":1.365059932},
{"learn":[10010.84434],"iteration":138,"passed_time":0.2197689324,"remaining_time":1.361302524},
{"learn":[10008.42277],"iteration":139,"passed_time":0.2209087725,"remaining_time":1.357011031},
{"learn":[10004.77281],"iteration":140,"passed_time":0.2222767755,"remaining_time":1.354154256},
{"learn":[10000.68298],"iteration":141,"passed_time":0.224472611,"remaining_time":1.356320424},
{"learn":[9998.307501],"iteration":142,"passed_time":0.2268805199,"remaining_time":1.359696543},
{"learn":[9995.233175],"iteration":143,"passed_time":0.2284401515,"remaining_time":1.357949789},
{"learn":[9990.124704],"iteration":144,"passed_time":0.2298859543,"remaining_time":1.35553442},
{"learn":[9985.475639],"iteration":145,"passed_time":0.2311032202,"remaining_time":1.351795548},
{"learn":[9980.124346],"iteration":146,"passed_time":0.2330085275,"remaining_time":1.352083497},
{"learn":[9977.587551],"iteration":147,"passed_time":0.2344719989,"remaining_time":1.349798264},
{"learn":[9972.894843],"iteration":148,"passed_time":0.2356814118,"remaining_time":1.34607303},
{"learn":[9965.389104],"iteration":149,"passed_time":0.2369238516,"remaining_time":1.342568492},
{"learn":[9960.327332],"iteration":150,"passed_time":0.2391597099,"remaining_time":1.344679429},
{"learn":[9956.986039],"iteration":151,"passed_time":0.241016387,"remaining_time":1.344617738},
{"learn":[9953.30375],"iteration":152,"passed_time":0.2425629659,"remaining_time":1.342815896},
{"learn":[9949.552242],"iteration":153,"passed_time":0.2441074512,"remaining_time":1.341005868},
{"learn":[9948.435264],"iteration":154,"passed_time":0.2454978283,"remaining_time":1.338359129},
{"learn":[9942.453339],"iteration":155,"passed_time":0.2469359887,"remaining_time":1.335987016},
{"learn":[9938.994145],"iteration":156,"passed_time":0.2484069969,"remaining_time":1.333803175},
{"learn":[9931.860904],"iteration":157,"passed_time":0.2496941751,"remaining_time":1.330648705},
{"learn":[9926.969871],"iteration":158,"passed_time":0.2510626078,"remaining_time":1.327947504},
{"learn":[9922.788745],"iteration":159,"passed_time":0.2525097685,"remaining_time":1.325676284},
{"learn":[9921.271942],"iteration":160,"passed_time":0.2546059161,"remaining_time":1.326797289},
{"learn":[9914.713718],"iteration":161,"passed_time":0.2571277454,"remaining_time":1.33008056},
{"learn":[9912.003836],"iteration":162,"passed_time":0.2587069553,"remaining_time":1.32845228},
{"learn":[9909.496515],"iteration":163,"passed_time":0.2601692345,"remaining_time":1.326228537},
{"learn":[9906.101079],"iteration":164,"passed_time":0.2615243549,"remaining_time":1.323471735},
{"learn":[9899.574215],"iteration":165,"passed_time":0.2630555242,"remaining_time":1.321616308},
{"learn":[9896.103248],"iteration":166,"passed_time":0.2642944549,"remaining_time":1.318307071},
{"learn":[9893.613614],"iteration":167,"passed_time":0.2655944947,"remaining_time":1.315325116},
{"learn":[9891.223167],"iteration":168,"passed_time":0.2669149102,"remaining_time":1.312463257},
{"learn":[9887.450343],"iteration":169,"passed_time":0.2689185819,"remaining_time":1.312955429},
{"learn":[9883.909733],"iteration":170,"passed_time":0.2714249377,"remaining_time":1.3158554},
{"learn":[9881.072326],"iteration":171,"passed_time":0.2733612696,"remaining_time":1.315948437},
{"learn":[9876.721751],"iteration":172,"passed_time":0.2751878852,"remaining_time":1.315493532},
{"learn":[9873.538689],"iteration":173,"passed_time":0.2769428759,"remaining_time":1.314682848},
{"learn":[9869.62335],"iteration":174,"passed_time":0.2785975918,"remaining_time":1.313388647},
{"learn":[9863.126402],"iteration":175,"passed_time":0.2797795361,"remaining_time":1.309876919},
{"learn":[9860.572373],"iteration":176,"passed_time":0.2810294885,"remaining_time":1.306707735},
{"learn":[9858.229406],"iteration":177,"passed_time":0.2823105794,"remaining_time":1.303703912},
{"learn":[9856.185343],"iteration":178,"passed_time":0.2837049875,"remaining_time":1.301239077},
{"learn":[9853.19725],"iteration":179,"passed_time":0.2857362509,"remaining_time":1.301687365},
{"learn":[9850.917897],"iteration":180,"passed_time":0.2876915706,"remaining_time":1.30176462},
{"learn":[9849.333598],"iteration":181,"passed_time":0.2893577863,"remaining_time":1.30052016},
{"learn":[9845.920049],"iteration":182,"passed_time":0.2908513307,"remaining_time":1.298500203},
{"learn":[9841.322694],"iteration":183,"passed_time":0.2924772154,"remaining_time":1.297072868},
{"learn":[9834.845644],"iteration":184,"passed_time":0.2937567277,"remaining_time":1.294117476},
{"learn":[9830.900849],"iteration":185,"passed_time":0.294996216,"remaining_time":1.291004945},
{"learn":[9827.153102],"iteration":186,"passed_time":0.29622287,"remaining_time":1.287856649},
{"learn":[9822.723172],"iteration":187,"passed_time":0.2974415981,"remaining_time":1.284694562},
{"learn":[9818.84645],"iteration":188,"passed_time":0.2990067701,"remaining_time":1.283039632},
{"learn":[9815.491467],"iteration":189,"passed_time":0.3008579433,"remaining_time":1.282604916},
{"learn":[9812.329591],"iteration":190,"passed_time":0.3030609042,"remaining_time":1.2836454},
{"learn":[9810.280067],"iteration":191,"passed_time":0.3046794054,"remaining_time":1.282192498},
{"learn":[9805.985991],"iteration":192,"passed_time":0.30602761,"remaining_time":1.279607675},
{"learn":[9803.674019],"iteration":193,"passed_time":0.3073360361,"remaining_time":1.276870336},
{"learn":[9800.564465],"iteration":194,"passed_time":0.3086971119,"remaining_time":1.274365},
{"learn":[9798.64284],"iteration":195,"passed_time":0.3098605997,"remaining_time":1.271060827},
{"learn":[9796.764139],"iteration":196,"passed_time":0.3111850756,"remaining_time":1.268434598},
{"learn":[9793.285885],"iteration":197,"passed_time":0.312378812,"remaining_time":1.265291956},
{"learn":[9789.767118],"iteration":198,"passed_time":0.3135788124,"remaining_time":1.262194114},
{"learn":[9785.845012],"iteration":199,"passed_time":0.315424525,"remaining_time":1.2616981},
{"learn":[9783.14021],"iteration":200,"passed_time":0.3175531737,"remaining_time":1.262313362},
{"learn":[9777.612492],"iteration":201,"passed_time":0.3191730906,"remaining_time":1.260891715},
{"learn":[9773.214236],"iteration":202,"passed_time":0.3207872166,"remaining_time":1.259445377},
{"learn":[9771.099259],"iteration":203,"passed_time":0.3220724667,"remaining_time":1.256714135},
{"learn":[9768.842435],"iteration":204,"passed_time":0.3235261523,"remaining_time":1.2546502},
{"learn":[9766.022876],"iteration":205,"passed_time":0.3251198695,"remaining_time":1.253131924},
{"learn":[9764.251343],"iteration":206,"passed_time":0.3263238913,"remaining_time":1.250120028},
{"learn":[9761.093088],"iteration":207,"passed_time":0.3274787581,"remaining_time":1.246938348},
{"learn":[9757.681692],"iteration":208,"passed_time":0.3286496013,"remaining_time":1.243836529},
{"learn":[9753.632685],"iteration":209,"passed_time":0.3302935981,"remaining_time":1.24253306},
{"learn":[9750.453798],"iteration":210,"passed_time":0.332648994,"remaining_time":1.243886522},
{"learn":[9746.803784],"iteration":211,"passed_time":0.3345215068,"remaining_time":1.243410129},
{"learn":[9742.243827],"iteration":212,"passed_time":0.3361540987,"remaining_time":1.242034158},
{"learn":[9734.25496],"iteration":213,"passed_time":0.3376075805,"remaining_time":1.239997936},
{"learn":[9729.817179],"iteration":214,"passed_time":0.338882695,"remaining_time":1.237315886},
{"learn":[9726.500362],"iteration":215,"passed_time":0.3402184848,"remaining_time":1.234867093},
{"learn":[9720.92497],"iteration":216,"passed_time":0.3419713755,"remaining_time":1.233933581},
{"learn":[9717.319488],"iteration":217,"passed_time":0.3434857568,"remaining_time":1.232136981},
{"learn":[9713.007421],"iteration":218,"passed_time":0.344850655,"remaining_time":1.22980987},
{"learn":[9709.199555],"iteration":219,"passed_time":0.3469430242,"remaining_time":1.230070722},
{"learn":[9705.495683],"iteration":220,"passed_time":0.3488023391,"remaining_time":1.229488788},
{"learn":[9701.831479],"iteration":221,"passed_time":0.3502962917,"remaining_time":1.227614932},
{"learn":[9699.281471],"iteration":222,"passed_time":0.3517320602,"remaining_time":1.225541752},
{"learn":[9696.686595],"iteration":223,"passed_time":0.3530116829,"remaining_time":1.22293333},
{"learn":[9693.521008],"iteration":224,"passed_time":0.3544549242,"remaining_time":1.220900294},
{"learn":[9691.985151],"iteration":225,"passed_time":0.3556664018,"remaining_time":1.218078739},
{"learn":[9689.992272],"iteration":226,"passed_time":0.3568464573,"remaining_time":1.215164368},
{"learn":[9686.988198],"iteration":227,"passed_time":0.3580062022,"remaining_time":1.212196439},
{"learn":[9684.871971],"iteration":228,"passed_time":0.3591773646,"remaining_time":1.209282743},
{"learn":[9682.148038],"iteration":229,"passed_time":0.3612700361,"remaining_time":1.209469251},
{"learn":[9679.852082],"iteration":230,"passed_time":0.3638841032,"remaining_time":1.211371755},
{"learn":[9677.499164],"iteration":231,"passed_time":0.3655591317,"remaining_time":1.210126781},
{"learn":[9673.1858],"iteration":232,"passed_time":0.3670391286,"remaining_time":1.208236101},
{"learn":[9671.128503],"iteration":233,"passed_time":0.3684246258,"remaining_time":1.206039587},
{"learn":[9667.864718],"iteration":234,"passed_time":0.3697981486,"remaining_time":1.203810994},
{"learn":[9662.618147],"iteration":235,"passed_time":0.3718743259,"remaining_time":1.203864343},
{"learn":[9660.719186],"iteration":236,"passed_time":0.3730868233,"remaining_time":1.201119182},
{"learn":[9655.620229],"iteration":237,"passed_time":0.3744023144,"remaining_time":1.198716654},
{"learn":[9652.171608],"iteration":238,"passed_time":0.3757972634,"remaining_time":1.196576224},
{"learn":[9649.164417],"iteration":239,"passed_time":0.3777895599,"remaining_time":1.196333606},
{"learn":[9643.574321],"iteration":240,"passed_time":0.3800774496,"remaining_time":1.197007404},
{"learn":[9642.266796],"iteration":241,"passed_time":0.3816339907,"remaining_time":1.195365971},
{"learn":[9640.293891],"iteration":242,"passed_time":0.3831360544,"remaining_time":1.193555527},
{"learn":[9635.783158],"iteration":243,"passed_time":0.3846251112,"remaining_time":1.191707312},
{"learn":[9633.903531],"iteration":244,"passed_time":0.3859049678,"remaining_time":1.18921735},
{"learn":[9630.652926],"iteration":245,"passed_time":0.3870895347,"remaining_time":1.186445159},
{"learn":[9624.509266],"iteration":246,"passed_time":0.3882645514,"remaining_time":1.183656709},
{"learn":[9619.378514],"iteration":247,"passed_time":0.3894216851,"remaining_time":1.180827045},
{"learn":[9616.982923],"iteration":248,"passed_time":0.390555955,"remaining_time":1.177941856},
{"learn":[9614.71779],"iteration":249,"passed_time":0.392733977,"remaining_time":1.178201931},
{"learn":[9611.457068],"iteration":250,"passed_time":0.3950369261,"remaining_time":1.178815369},
{"learn":[9607.604728],"iteration":251,"passed_time":0.3966450235,"remaining_time":1.177343165},
{"learn":[9605.841848],"iteration":252,"passed_time":0.3982917101,"remaining_time":1.175983824},
{"learn":[9601.375726],"iteration":253,"passed_time":0.3997110198,"remaining_time":1.173954412},
{"learn":[9599.203257],"iteration":254,"passed_time":0.401231335,"remaining_time":1.172224881},
{"learn":[9596.49861],"iteration":255,"passed_time":0.4025932023,"remaining_time":1.170036494},
{"learn":[9594.203793],"iteration":256,"passed_time":0.403885015,"remaining_time":1.167652008},
{"learn":[9590.767379],"iteration":257,"passed_time":0.4050934454,"remaining_time":1.165036188},
{"learn":[9588.02538],"iteration":258,"passed_time":0.406503167,"remaining_time":1.16300713},
{"learn":[9581.84121],"iteration":259,"passed_time":0.4084716759,"remaining_time":1.162573232},
{"learn":[9578.56985],"iteration":260,"passed_time":0.4108496251,"remaining_time":1.163286869},
{"learn":[9572.335999],"iteration":261,"passed_time":0.4124041078,"remaining_time":1.161657372},
{"learn":[9569.068283],"iteration":262,"passed_time":0.4138929481,"remaining_time":1.159844497},
{"learn":[9566.559841],"iteration":263,"passed_time":0.4155277755,"remaining_time":1.158441071},
{"learn":[9564.124122],"iteration":264,"passed_time":0.41682704,"remaining_time":1.156105187},
{"learn":[9560.272306],"iteration":265,"passed_time":0.4180373862,"remaining_time":1.153531735},
{"learn":[9557.366192],"iteration":266,"passed_time":0.4192284316,"remaining_time":1.150915507},
{"learn":[9554.019903],"iteration":267,"passed_time":0.4204602949,"remaining_time":1.148421403},
{"learn":[9551.954472],"iteration":268,"passed_time":0.4229577128,"remaining_time":1.149375792},
{"learn":[9549.892502],"iteration":269,"passed_time":0.4253468651,"remaining_time":1.150011895},
{"learn":[9547.760348],"iteration":270,"passed_time":0.4269963233,"remaining_time":1.148635866},
{"learn":[9544.854458],"iteration":271,"passed_time":0.4284810704,"remaining_time":1.146816982},
{"learn":[9542.442599],"iteration":272,"passed_time":0.4299921006,"remaining_time":1.145070539},
{"learn":[9539.152657],"iteration":273,"passed_time":0.4313958846,"remaining_time":1.143041651},
{"learn":[9535.817968],"iteration":274,"passed_time":0.4329247367,"remaining_time":1.141347033},
{"learn":[9533.981063],"iteration":275,"passed_time":0.4341864859,"remaining_time":1.138952956},
{"learn":[9531.240514],"iteration":276,"passed_time":0.4353527847,"remaining_time":1.136317918},
{"learn":[9528.922138],"iteration":277,"passed_time":0.436738459,"remaining_time":1.134263192},
{"learn":[9527.01309],"iteration":278,"passed_time":0.438868423,"remaining_time":1.134136677},
{"learn":[9521.559076],"iteration":279,"passed_time":0.440789134,"remaining_time":1.133457773},
{"learn":[9517.570857],"iteration":280,"passed_time":0.4421789886,"remaining_time":1.131411718},
{"learn":[9515.488219],"iteration":281,"passed_time":0.4437554336,"remaining_time":1.129845395},
{"learn":[9514.152839],"iteration":282,"passed_time":0.4450745704,"remaining_time":1.127627092},
{"learn":[9511.029108],"iteration":283,"passed_time":0.446507304,"remaining_time":1.125701513},
{"learn":[9509.026037],"iteration":284,"passed_time":0.4478667912,"remaining_time":1.123595634},
{"learn":[9506.801597],"iteration":285,"passed_time":0.448981621,"remaining_time":1.120884187},
{"learn":[9502.033131],"iteration":286,"passed_time":0.4502134644,"remaining_time":1.118474565},
{"learn":[9499.408782],"iteration":287,"passed_time":0.4513730897,"remaining_time":1.115894583},
{"learn":[9495.967829],"iteration":288,"passed_time":0.4526257811,"remaining_time":1.113553392},
{"learn":[9493.653931],"iteration":289,"passed_time":0.4548036686,"remaining_time":1.113484844},
{"learn":[9488.747343],"iteration":290,"passed_time":0.4571212211,"remaining_time":1.113742082},
{"learn":[9485.528799],"iteration":291,"passed_time":0.4587933604,"remaining_time":1.112416778},
{"learn":[9482.544533],"iteration":292,"passed_time":0.4602065256,"remaining_time":1.11046421},
{"learn":[9480.062212],"iteration":293,"passed_time":0.4618923379,"remaining_time":1.109170036},
{"learn":[9476.227354],"iteration":294,"passed_time":0.4633105959,"remaining_time":1.107233797},
{"learn":[9473.725346],"iteration":295,"passed_time":0.4645277187,"remaining_time":1.104822682},
{"learn":[9469.414708],"iteration":296,"passed_time":0.4657603179,"remaining_time":1.102456241},
{"learn":[9465.296472],"iteration":297,"passed_time":0.4669224206,"remaining_time":1.09993134},
{"learn":[9460.897805],"iteration":298,"passed_time":0.4686409357,"remaining_time":1.098720053},
{"learn":[9456.011855],"iteration":299,"passed_time":0.4711773773,"remaining_time":1.09941388},
{"learn":[9452.788556],"iteration":300,"passed_time":0.4728021401,"remaining_time":1.097969089},
{"learn":[9450.976753],"iteration":301,"passed_time":0.4751439031,"remaining_time":1.098180279},
{"learn":[9447.697398],"iteration":302,"passed_time":0.4769130572,"remaining_time":1.097057429},
{"learn":[9445.231353],"iteration":303,"passed_time":0.4781737676,"remaining_time":1.094766257},
{"learn":[9441.934838],"iteration":304,"passed_time":0.4793641375,"remaining_time":1.092321559},
{"learn":[9439.425756],"iteration":305,"passed_time":0.4806004682,"remaining_time":1.089989297},
{"learn":[9437.267837],"iteration":306,"passed_time":0.481760437,"remaining_time":1.087491801},
{"learn":[9433.535758],"iteration":307,"passed_time":0.4831614697,"remaining_time":1.085544601},
{"learn":[9431.218224],"iteration":308,"passed_time":0.4852690004,"remaining_time":1.085180839},
{"learn":[9428.897485],"iteration":309,"passed_time":0.487794896,"remaining_time":1.085737027},
{"learn":[9426.210028],"iteration":310,"passed_time":0.489303732,"remaining_time":1.084020165},
{"learn":[9423.880668],"iteration":311,"passed_time":0.4909442722,"remaining_time":1.082595062},
{"learn":[9419.691899],"iteration":312,"passed_time":0.4925171418,"remaining_time":1.081020053},
{"learn":[9416.574263],"iteration":313,"passed_time":0.4941497794,"remaining_time":1.079575633},
{"learn":[9415.023369],"iteration":314,"passed_time":0.4957875281,"remaining_time":1.078141133},
{"learn":[9413.202233],"iteration":315,"passed_time":0.4975507046,"remaining_time":1.076976842},
{"learn":[9409.83778],"iteration":316,"passed_time":0.4988256415,"remaining_time":1.074756824},
{"learn":[9405.993],"iteration":317,"passed_time":0.5011909614,"remaining_time":1.074881244},
{"learn":[9402.860479],"iteration":318,"passed_time":0.5027643921,"remaining_time":1.073299533},
{"learn":[9400.453351],"iteration":319,"passed_time":0.5039617778,"remaining_time":1.070918778},
{"learn":[9398.278306],"iteration":320,"passed_time":0.5051477034,"remaining_time":1.068521154},
{"learn":[9394.077014],"iteration":321,"passed_time":0.5063247458,"remaining_time":1.066112353},
{"learn":[9391.108416],"iteration":322,"passed_time":0.5076505994,"remaining_time":1.064023083},
{"learn":[9387.47918],"iteration":323,"passed_time":0.5089313479,"remaining_time":1.061844417},
{"learn":[9384.911043],"iteration":324,"passed_time":0.5101555584,"remaining_time":1.059553852},
{"learn":[9380.044809],"iteration":325,"passed_time":0.5113559258,"remaining_time":1.057220534},
{"learn":[9378.460696],"iteration":326,"passed_time":0.5125640734,"remaining_time":1.054910157},
{"learn":[9373.901911],"iteration":327,"passed_time":0.5139654008,"remaining_time":1.053002285},
{"learn":[9370.659891],"iteration":328,"passed_time":0.5157101721,"remaining_time":1.05179795},
{"learn":[9366.918647],"iteration":329,"passed_time":0.5171954918,"remaining_time":1.050063574},
{"learn":[9364.262402],"iteration":330,"passed_time":0.5185459828,"remaining_time":1.048058195},
{"learn":[9361.236887],"iteration":331,"passed_time":0.5197389813,"remaining_time":1.045739878},
{"learn":[9356.493685],"iteration":332,"passed_time":0.5208893494,"remaining_time":1.043342931},
{"learn":[9352.995482],"iteration":333,"passed_time":0.5224148325,"remaining_time":1.041701433},
{"learn":[9348.641431],"iteration":334,"passed_time":0.5237733194,"remaining_time":1.039729127},
{"learn":[9346.536021],"iteration":335,"passed_time":0.524957436,"remaining_time":1.037415885},
{"learn":[9342.19284],"iteration":336,"passed_time":0.5268362418,"remaining_time":1.036476048},
{"learn":[9340.579183],"iteration":337,"passed_time":0.5282482906,"remaining_time":1.034616475},
{"learn":[9338.156749],"iteration":338,"passed_time":0.5298998537,"remaining_time":1.033226558},
{"learn":[9333.114846],"iteration":339,"passed_time":0.5317334636,"remaining_time":1.032188488},
{"learn":[9330.255375],"iteration":340,"passed_time":0.5332025004,"remaining_time":1.030441196},
{"learn":[9325.499427],"iteration":341,"passed_time":0.5350261899,"remaining_time":1.029377874},
{"learn":[9322.47986],"iteration":342,"passed_time":0.5362751724,"remaining_time":1.027209295},
{"learn":[9320.463824],"iteration":343,"passed_time":0.5375328038,"remaining_time":1.025062556},
{"learn":[9317.799637],"iteration":344,"passed_time":0.5388102943,"remaining_time":1.022958675},
{"learn":[9314.821296],"iteration":345,"passed_time":0.5406928562,"remaining_time":1.02200326},
{"learn":[9310.121037],"iteration":346,"passed_time":0.5420941637,"remaining_time":1.020136856},
{"learn":[9307.114024],"iteration":347,"passed_time":0.5433596762,"remaining_time":1.018018704},
{"learn":[9304.94724],"iteration":348,"passed_time":0.5445996224,"remaining_time":1.015857748},
{"learn":[9302.56124],"iteration":349,"passed_time":0.5464918057,"remaining_time":1.014913353},
{"learn":[9299.209354],"iteration":350,"passed_time":0.5482843304,"remaining_time":1.013779289},
{"learn":[9296.748594],"iteration":351,"passed_time":0.5499407135,"remaining_time":1.012390859},
{"learn":[9294.226842],"iteration":352,"passed_time":0.5515758157,"remaining_time":1.010961906},
{"learn":[9291.312576],"iteration":353,"passed_time":0.5528801334,"remaining_time":1.008928153},
{"learn":[9288.511511],"iteration":354,"passed_time":0.5545627118,"remaining_time":1.007585772},
{"learn":[9286.905212],"iteration":355,"passed_time":0.5560556943,"remaining_time":1.005898503},
{"learn":[9285.503141],"iteration":356,"passed_time":0.5574780356,"remaining_time":1.004085089},
{"learn":[9282.940029],"iteration":357,"passed_time":0.5589207682,"remaining_time":1.002310428},
{"learn":[9280.645272],"iteration":358,"passed_time":0.5601807955,"remaining_time":1.000211392},
{"learn":[9275.683871],"iteration":359,"passed_time":0.5619864519,"remaining_time":0.9990870256},
{"learn":[9273.017507],"iteration":360,"passed_time":0.5637953509,"remaining_time":0.9979646239},
{"learn":[9271.006307],"iteration":361,"passed_time":0.5654877524,"remaining_time":0.9966331107},
{"learn":[9267.471695],"iteration":362,"passed_time":0.5673190538,"remaining_time":0.9955433534},
{"learn":[9265.194429],"iteration":363,"passed_time":0.5691658565,"remaining_time":0.9944766064},
{"learn":[9261.693447],"iteration":364,"passed_time":0.5705579565,"remaining_time":0.992614527},
{"learn":[9258.830449],"iteration":365,"passed_time":0.5721635071,"remaining_time":0.9911247636},
{"learn":[9256.065155],"iteration":366,"passed_time":0.5738996514,"remaining_time":0.9898596168},
{"learn":[9253.98658],"iteration":367,"passed_time":0.5755828645,"remaining_time":0.9885010064},
{"learn":[9250.332237],"iteration":368,"passed_time":0.5777335788,"remaining_time":0.9879400764},
{"learn":[9248.448164],"iteration":369,"passed_time":0.5796886078,"remaining_time":0.9870373592},
{"learn":[9247.007754],"iteration":370,"passed_time":0.5811008635,"remaining_time":0.9852087416},
{"learn":[9244.755618],"iteration":371,"passed_time":0.5828378486,"remaining_time":0.9839305616},
{"learn":[9243.536193],"iteration":372,"passed_time":0.5842925183,"remaining_time":0.9821753591},
{"learn":[9241.778588],"iteration":373,"passed_time":0.5856758193,"remaining_time":0.9803023072},
{"learn":[9239.249963],"iteration":374,"passed_time":0.5874295138,"remaining_time":0.9790491897},
{"learn":[9237.753074],"iteration":375,"passed_time":0.5886982796,"remaining_time":0.9769886343},
{"learn":[9235.729311],"iteration":376,"passed_time":0.589875479,"remaining_time":0.9747809639},
{"learn":[9233.884773],"iteration":377,"passed_time":0.5914148674,"remaining_time":0.9731747289},
{"learn":[9229.789952],"iteration":378,"passed_time":0.5932868865,"remaining_time":0.9721138695},
{"learn":[9226.737051],"iteration":379,"passed_time":0.5955829314,"remaining_time":0.9717405723},
{"learn":[9224.728137],"iteration":380,"passed_time":0.597385236,"remaining_time":0.970555016},
{"learn":[9220.804068],"iteration":381,"passed_time":0.5989203691,"remaining_time":0.9689340003},
{"learn":[9218.3404],"iteration":382,"passed_time":0.6002207099,"remaining_time":0.9669351907},
{"learn":[9216.266511],"iteration":383,"passed_time":0.6016164353,"remaining_time":0.9650930316},
{"learn":[9215.322477],"iteration":384,"passed_time":0.6033422768,"remaining_time":0.9637805201},
{"learn":[9213.700468],"iteration":385,"passed_time":0.6046069188,"remaining_time":0.961732249},
{"learn":[9211.401904],"iteration":386,"passed_time":0.6058711752,"remaining_time":0.959687417},
{"learn":[9207.401742],"iteration":387,"passed_time":0.6078457801,"remaining_time":0.9587670553},
{"learn":[9205.341749],"iteration":388,"passed_time":0.6096610432,"remaining_time":0.9575909959},
{"learn":[9202.657478],"iteration":389,"passed_time":0.6119235993,"remaining_time":0.9571112707},
{"learn":[9200.654431],"iteration":390,"passed_time":0.6132832704,"remaining_time":0.9552161425},
{"learn":[9196.6717],"iteration":391,"passed_time":0.6146760022,"remaining_time":0.9533750239},
{"learn":[9194.781357],"iteration":392,"passed_time":0.6160121606,"remaining_time":0.9514488079},
{"learn":[9192.494502],"iteration":393,"passed_time":0.6176496837,"remaining_time":0.9499891075},
{"learn":[9190.516947],"iteration":394,"passed_time":0.6198235903,"remaining_time":0.949350056},
{"learn":[9185.989101],"iteration":395,"passed_time":0.6212188327,"remaining_time":0.9475155934},
{"learn":[9182.026466],"iteration":396,"passed_time":0.6230618674,"remaining_time":0.9463634914},
{"learn":[9180.500892],"iteration":397,"passed_time":0.6251927012,"remaining_time":0.9456432314},
{"learn":[9176.221434],"iteration":398,"passed_time":0.6265643308,"remaining_time":0.9437723379},
{"learn":[9174.317017],"iteration":399,"passed_time":0.628098344,"remaining_time":0.942147516},
{"learn":[9172.245463],"iteration":400,"passed_time":0.6294655726,"remaining_time":0.9402740099},
{"learn":[9170.785751],"iteration":401,"passed_time":0.6311455173,"remaining_time":0.9388682073},
{"learn":[9169.235778],"iteration":402,"passed_time":0.632953031,"remaining_time":0.9376500237},
{"learn":[9164.522033],"iteration":403,"passed_time":0.6343559871,"remaining_time":0.9358320997},
{"learn":[9160.444542],"iteration":404,"passed_time":0.6356214638,"remaining_time":0.9338142493},
{"learn":[9158.119602],"iteration":405,"passed_time":0.6370477952,"remaining_time":0.9320354442},
{"learn":[9152.679859],"iteration":406,"passed_time":0.6390367514,"remaining_time":0.9310781169},
{"learn":[9149.66917],"iteration":407,"passed_time":0.6411222832,"remaining_time":0.9302558619},
{"learn":[9146.769755],"iteration":408,"passed_time":0.6427554371,"remaining_time":0.9287737489},
{"learn":[9144.079623],"iteration":409,"passed_time":0.6443651874,"remaining_time":0.9272572209},
{"learn":[9140.181625],"iteration":410,"passed_time":0.6458870943,"remaining_time":0.9256143517},
{"learn":[9137.927561],"iteration":411,"passed_time":0.6474203355,"remaining_time":0.9239882458},
{"learn":[9134.081644],"iteration":412,"passed_time":0.6491081799,"remaining_time":0.9225823284},
{"learn":[9132.064544],"iteration":413,"passed_time":0.6517007719,"remaining_time":0.922455682},
{"learn":[9130.948617],"iteration":414,"passed_time":0.653661283,"remaining_time":0.9214261459},
{"learn":[9126.550995],"iteration":415,"passed_time":0.655620692,"remaining_time":0.9203905869},
{"learn":[9122.968615],"iteration":416,"passed_time":0.6577989817,"remaining_time":0.9196566099},
{"learn":[9118.02446],"iteration":417,"passed_time":0.65941738,"remaining_time":0.9181361607},
{"learn":[9113.893034],"iteration":418,"passed_time":0.6609548451,"remaining_time":0.9165030191},
{"learn":[9111.797984],"iteration":419,"passed_time":0.662431551,"remaining_time":0.9147864276},
{"learn":[9108.532549],"iteration":420,"passed_time":0.6637310221,"remaining_time":0.9128272252},
{"learn":[9104.613543],"iteration":421,"passed_time":0.6652507706,"remaining_time":0.9111728564},
{"learn":[9102.061761],"iteration":422,"passed_time":0.6670791356,"remaining_time":0.9099400974},
{"learn":[9100.389915],"iteration":423,"passed_time":0.6686995962,"remaining_time":0.908422093},
{"learn":[9097.812946],"iteration":424,"passed_time":0.6711763957,"remaining_time":0.9080621824},
{"learn":[9095.526176],"iteration":425,"passed_time":0.6730654614,"remaining_time":0.9069004105},
{"learn":[9091.359501],"iteration":426,"passed_time":0.6747771864,"remaining_time":0.9054972548},
{"learn":[9088.684187],"iteration":427,"passed_time":0.676140527,"remaining_time":0.9036270595},
{"learn":[9087.17956],"iteration":428,"passed_time":0.6775289785,"remaining_time":0.9017926497},
{"learn":[9083.956017],"iteration":429,"passed_time":0.6790107824,"remaining_time":0.9000840604},
{"learn":[9080.31809],"iteration":430,"passed_time":0.680652651,"remaining_time":0.8985878385},
{"learn":[9077.884096],"iteration":431,"passed_time":0.6819276768,"remaining_time":0.8966086121},
{"learn":[9073.141874],"iteration":432,"passed_time":0.6834548657,"remaining_time":0.894962838},
{"learn":[9070.30734],"iteration":433,"passed_time":0.6853724116,"remaining_time":0.8938266934},
{"learn":[9069.060944],"iteration":434,"passed_time":0.6876043208,"remaining_time":0.8930952672},
{"learn":[9063.793188],"iteration":435,"passed_time":0.6891626219,"remaining_time":0.8914855935},
{"learn":[9061.51697],"iteration":436,"passed_time":0.6905393544,"remaining_time":0.8896422346},
{"learn":[9060.600291],"iteration":437,"passed_time":0.6918762653,"remaining_time":0.8877499112},
{"learn":[9056.986611],"iteration":438,"passed_time":0.6932618506,"remaining_time":0.8859223194},
{"learn":[9054.070456],"iteration":439,"passed_time":0.6949268194,"remaining_time":0.8844523155},
{"learn":[9052.494178],"iteration":440,"passed_time":0.6964491774,"remaining_time":0.882800658},
{"learn":[9051.314087],"iteration":441,"passed_time":0.6978728071,"remaining_time":0.8810249465},
{"learn":[9049.461378],"iteration":442,"passed_time":0.6999475503,"remaining_time":0.8800694933},
{"learn":[9046.902375],"iteration":443,"passed_time":0.7019894132,"remaining_time":0.8790678238},
{"learn":[9045.261092],"iteration":444,"passed_time":0.7034512825,"remaining_time":0.8773381164},
{"learn":[9043.988582],"iteration":445,"passed_time":0.7049853442,"remaining_time":0.875699284},
{"learn":[9041.528007],"iteration":446,"passed_time":0.706279,"remaining_time":0.8737635056},
{"learn":[9039.039311],"iteration":447,"passed_time":0.7078004677,"remaining_time":0.8721112906},
{"learn":[9036.589298],"iteration":448,"passed_time":0.7098035385,"remaining_time":0.8710506675},
{"learn":[9034.254298],"iteration":449,"passed_time":0.7111254997,"remaining_time":0.8691533886},
{"learn":[9033.318146],"iteration":450,"passed_time":0.7123615095,"remaining_time":0.8671540327},
{"learn":[9029.274648],"iteration":451,"passed_time":0.7142356406,"remaining_time":0.8659317059},
{"learn":[9026.269013],"iteration":452,"passed_time":0.7159909332,"remaining_time":0.8645630033},
{"learn":[9022.941586],"iteration":453,"passed_time":0.7174765425,"remaining_time":0.8628682647},
{"learn":[9021.136495],"iteration":454,"passed_time":0.7194128105,"remaining_time":0.8617142455},
{"learn":[9019.204507],"iteration":455,"passed_time":0.7209108814,"remaining_time":0.8600340339},
{"learn":[9016.503373],"iteration":456,"passed_time":0.7229932325,"remaining_time":0.8590488518},
{"learn":[9015.046001],"iteration":457,"passed_time":0.7245996855,"remaining_time":0.8574956976},
{"learn":[9011.097907],"iteration":458,"passed_time":0.7258940009,"remaining_time":0.8555744107},
{"learn":[9009.100326],"iteration":459,"passed_time":0.7272220602,"remaining_time":0.8536954619},
{"learn":[9007.441677],"iteration":460,"passed_time":0.7294764194,"remaining_time":0.8529019307},
{"learn":[9003.396901],"iteration":461,"passed_time":0.7317036441,"remaining_time":0.8520704773},
{"learn":[9000.887422],"iteration":462,"passed_time":0.7336115658,"remaining_time":0.8508626584},
{"learn":[8998.667499],"iteration":463,"passed_time":0.7352843699,"remaining_time":0.8493802204},
{"learn":[8996.927292],"iteration":464,"passed_time":0.7369573151,"remaining_time":0.847897126},
{"learn":[8992.682504],"iteration":465,"passed_time":0.7385011558,"remaining_time":0.8462652729},
{"learn":[8990.411937],"iteration":466,"passed_time":0.7407248288,"remaining_time":0.8454097083},
{"learn":[8986.705055],"iteration":467,"passed_time":0.7427594825,"remaining_time":0.8443334289},
{"learn":[8984.082846],"iteration":468,"passed_time":0.7456222952,"remaining_time":0.844190701},
{"learn":[8979.73659],"iteration":469,"passed_time":0.7478164961,"remaining_time":0.8432824318},
{"learn":[8978.504315],"iteration":470,"passed_time":0.749594087,"remaining_time":0.8419007899},
{"learn":[8976.518344],"iteration":471,"passed_time":0.7511406052,"remaining_time":0.8402589821},
{"learn":[8974.753243],"iteration":472,"passed_time":0.7525503133,"remaining_time":0.8384651482},
{"learn":[8972.652702],"iteration":473,"passed_time":0.7541658701,"remaining_time":0.8369013664},
{"learn":[8970.139656],"iteration":474,"passed_time":0.7558433724,"remaining_time":0.8354058326},
{"learn":[8968.002195],"iteration":475,"passed_time":0.7571501789,"remaining_time":0.8335014575},
{"learn":[8964.222325],"iteration":476,"passed_time":0.7589228966,"remaining_time":0.8321104296},
{"learn":[8960.276038],"iteration":477,"passed_time":0.7611325885,"remaining_time":0.8311950025},
{"learn":[8958.276958],"iteration":478,"passed_time":0.7629839638,"remaining_time":0.8298844367},
{"learn":[8955.79065],"iteration":479,"passed_time":0.7646908735,"remaining_time":0.828415113},
{"learn":[8954.939093],"iteration":480,"passed_time":0.7665471936,"remaining_time":0.8271060155},
{"learn":[8952.226976],"iteration":481,"passed_time":0.7679950949,"remaining_time":0.8253557244},
{"learn":[8948.124979],"iteration":482,"passed_time":0.7696609476,"remaining_time":0.8238399791},
{"learn":[8945.804716],"iteration":483,"passed_time":0.7712823947,"remaining_time":0.8222762721},
{"learn":[8942.099958],"iteration":484,"passed_time":0.7736085007,"remaining_time":0.8214605729},
{"learn":[8940.083037],"iteration":485,"passed_time":0.775776119,"remaining_time":0.8204710395},
{"learn":[8938.225851],"iteration":486,"passed_time":0.7776409405,"remaining_time":0.8191577053},
{"learn":[8935.140171],"iteration":487,"passed_time":0.7795722078,"remaining_time":0.8179118246},
{"learn":[8934.185092],"iteration":488,"passed_time":0.7812705541,"remaining_time":0.8164197406},
{"learn":[8931.398117],"iteration":489,"passed_time":0.7828014144,"remaining_time":0.8147524925},
{"learn":[8927.059856],"iteration":490,"passed_time":0.7847172196,"remaining_time":0.813484857},
{"learn":[8925.256804],"iteration":491,"passed_time":0.786298885,"remaining_time":0.8118695805},
{"learn":[8924.053674],"iteration":492,"passed_time":0.787781262,"remaining_time":0.8101523323},
{"learn":[8922.236478],"iteration":493,"passed_time":0.7898416007,"remaining_time":0.8090280364},
{"learn":[8920.346533],"iteration":494,"passed_time":0.7924317377,"remaining_time":0.8084404596},
{"learn":[8918.541507],"iteration":495,"passed_time":0.7941117999,"remaining_time":0.8069200547},
{"learn":[8916.701435],"iteration":496,"passed_time":0.7958849631,"remaining_time":0.8054932323},
{"learn":[8915.316957],"iteration":497,"passed_time":0.7974624836,"remaining_time":0.8038678047},
{"learn":[8912.665271],"iteration":498,"passed_time":0.7989715801,"remaining_time":0.802173871},
{"learn":[8908.397065],"iteration":499,"passed_time":0.8013854771,"remaining_time":0.8013854771},
{"learn":[8907.263109],"iteration":500,"passed_time":0.8032982847,"remaining_time":0.8000915052},
{"learn":[8904.278236],"iteration":501,"passed_time":0.8051868096,"remaining_time":0.7987709785},
{"learn":[8898.954222],"iteration":502,"passed_time":0.8074861583,"remaining_time":0.7978541166},
{"learn":[8895.416029],"iteration":503,"passed_time":0.8091894095,"remaining_time":0.7963451332},
{"learn":[8892.620781],"iteration":504,"passed_time":0.8106132648,"remaining_time":0.7945615169},
{"learn":[8890.053993],"iteration":505,"passed_time":0.8119887831,"remaining_time":0.7927321321},
{"learn":[8887.422372],"iteration":506,"passed_time":0.8132889945,"remaining_time":0.7908313102},
{"learn":[8885.244535],"iteration":507,"passed_time":0.8147160164,"remaining_time":0.7890556695},
{"learn":[8882.385848],"iteration":508,"passed_time":0.8160280572,"remaining_time":0.7871704835},
{"learn":[8879.895791],"iteration":509,"passed_time":0.8174586681,"remaining_time":0.7854014654},
{"learn":[8877.257457],"iteration":510,"passed_time":0.8189993063,"remaining_time":0.7837390622},
{"learn":[8875.384898],"iteration":511,"passed_time":0.8208482968,"remaining_time":0.7823710329},
{"learn":[8874.38565],"iteration":512,"passed_time":0.8223803879,"remaining_time":0.7807002903},
{"learn":[8873.243205],"iteration":513,"passed_time":0.8239662752,"remaining_time":0.7790809528},
{"learn":[8871.802332],"iteration":514,"passed_time":0.8257014104,"remaining_time":0.7776022991},
{"learn":[8869.748243],"iteration":515,"passed_time":0.8275931707,"remaining_time":0.7762695633},
{"learn":[8867.094459],"iteration":516,"passed_time":0.8289320654,"remaining_time":0.7744181578},
{"learn":[8865.251109],"iteration":517,"passed_time":0.8302241549,"remaining_time":0.7725251789},
{"learn":[8861.582517],"iteration":518,"passed_time":0.8315544242,"remaining_time":0.7706698999},
{"learn":[8858.406955],"iteration":519,"passed_time":0.8327776439,"remaining_time":0.7687178251},
{"learn":[8857.316772],"iteration":520,"passed_time":0.8342350581,"remaining_time":0.7669838634},
{"learn":[8854.725015],"iteration":521,"passed_time":0.8361652396,"remaining_time":0.7656838784},
{"learn":[8852.516329],"iteration":522,"passed_time":0.8379602338,"remaining_time":0.7642581864},
{"learn":[8851.191947],"iteration":523,"passed_time":0.8394559914,"remaining_time":0.7625592593},
{"learn":[8848.7133],"iteration":524,"passed_time":0.8408306837,"remaining_time":0.760751571},
{"learn":[8846.676476],"iteration":525,"passed_time":0.8422690955,"remaining_time":0.7590029492},
{"learn":[8843.627632],"iteration":526,"passed_time":0.8445034634,"remaining_time":0.7579699017},
{"learn":[8841.945712],"iteration":527,"passed_time":0.8460904583,"remaining_time":0.7563535915},
{"learn":[8839.48855],"iteration":528,"passed_time":0.8475559622,"remaining_time":0.7546292216},
{"learn":[8836.57991],"iteration":529,"passed_time":0.848803504,"remaining_time":0.7527125413},
{"learn":[8835.427144],"iteration":530,"passed_time":0.8505845341,"remaining_time":0.7512695791},
{"learn":[8833.879973],"iteration":531,"passed_time":0.8524929296,"remaining_time":0.7499373892},
{"learn":[8829.474507],"iteration":532,"passed_time":0.8541425824,"remaining_time":0.7483763339},
{"learn":[8823.868935],"iteration":533,"passed_time":0.855616797,"remaining_time":0.7466618491},
{"learn":[8821.959933],"iteration":534,"passed_time":0.8569314542,"remaining_time":0.7448095817},
{"learn":[8819.642853],"iteration":535,"passed_time":0.858818653,"remaining_time":0.7434549533},
{"learn":[8817.130019],"iteration":536,"passed_time":0.8602979021,"remaining_time":0.7417466084},
{"learn":[8815.533363],"iteration":537,"passed_time":0.8615761583,"remaining_time":0.7398665151},
{"learn":[8813.001775],"iteration":538,"passed_time":0.8628858616,"remaining_time":0.7380155513},
{"learn":[8811.672559],"iteration":539,"passed_time":0.8642503678,"remaining_time":0.7362132763},
{"learn":[8810.432079],"iteration":540,"passed_time":0.8658240492,"remaining_time":0.7345900898},
{"learn":[8808.550963],"iteration":541,"passed_time":0.8677510452,"remaining_time":0.7332656434},
{"learn":[8807.549403],"iteration":542,"passed_time":0.869152701,"remaining_time":0.7314968405},
{"learn":[8805.118819],"iteration":543,"passed_time":0.870756575,"remaining_time":0.7298988937},
{"learn":[8802.649275],"iteration":544,"passed_time":0.8721939455,"remaining_time":0.7281619178},
{"learn":[8801.034914],"iteration":545,"passed_time":0.8746149702,"remaining_time":0.7272439496},
{"learn":[8798.890321],"iteration":546,"passed_time":0.8763437806,"remaining_time":0.725747226},
{"learn":[8796.623936],"iteration":547,"passed_time":0.8777189801,"remaining_time":0.7239579909},
{"learn":[8795.071056],"iteration":548,"passed_time":0.8789360192,"remaining_time":0.7220403363},
{"learn":[8792.771866],"iteration":549,"passed_time":0.880662977,"remaining_time":0.7205424357},
{"learn":[8790.926671],"iteration":550,"passed_time":0.8828064972,"remaining_time":0.7193831529},
{"learn":[8788.469446],"iteration":551,"passed_time":0.8843842639,"remaining_time":0.7177611417},
{"learn":[8786.62604],"iteration":552,"passed_time":0.8859163859,"remaining_time":0.7161023951},
{"learn":[8786.146143],"iteration":553,"passed_time":0.8871400611,"remaining_time":0.7141957893},
{"learn":[8783.146711],"iteration":554,"passed_time":0.8886903965,"remaining_time":0.7125535612},
{"learn":[8781.112085],"iteration":555,"passed_time":0.890604595,"remaining_time":0.7112022305},
{"learn":[8778.046998],"iteration":556,"passed_time":0.8919745304,"remaining_time":0.7094160089},
{"learn":[8773.382093],"iteration":557,"passed_time":0.8933190171,"remaining_time":0.7076111211},
{"learn":[8769.876227],"iteration":558,"passed_time":0.8946158187,"remaining_time":0.7057702612},
{"learn":[8768.608398],"iteration":559,"passed_time":0.8962767497,"remaining_time":0.7042174462},
{"learn":[8766.532091],"iteration":560,"passed_time":0.8981313124,"remaining_time":0.7028157685},
{"learn":[8762.878388],"iteration":561,"passed_time":0.8995673025,"remaining_time":0.7010862606},
{"learn":[8761.691712],"iteration":562,"passed_time":0.9010192391,"remaining_time":0.6993701731},
{"learn":[8759.736747],"iteration":563,"passed_time":0.9025304945,"remaining_time":0.6977008787},
{"learn":[8757.663432],"iteration":564,"passed_time":0.9041617059,"remaining_time":0.6961244993},
{"learn":[8755.472505],"iteration":565,"passed_time":0.9060782884,"remaining_time":0.6947667441},
{"learn":[8752.676951],"iteration":566,"passed_time":0.9074648499,"remaining_time":0.6930022575},
{"learn":[8750.62177],"iteration":567,"passed_time":0.9088649799,"remaining_time":0.6912494213},
{"learn":[8747.081377],"iteration":568,"passed_time":0.9103020148,"remaining_time":0.6895257792},
{"learn":[8742.608603],"iteration":569,"passed_time":0.9119746879,"remaining_time":0.6879809049},
{"learn":[8737.26298],"iteration":570,"passed_time":0.9140116609,"remaining_time":0.6867092864},
{"learn":[8736.494727],"iteration":571,"passed_time":0.9154079633,"remaining_time":0.6849556089},
{"learn":[8735.717892],"iteration":572,"passed_time":0.9169269056,"remaining_time":0.6832945702},
{"learn":[8734.38945],"iteration":573,"passed_time":0.9182533564,"remaining_time":0.681491167},
{"learn":[8732.868678],"iteration":574,"passed_time":0.9204244699,"remaining_time":0.6803137387},
{"learn":[8730.264594],"iteration":575,"passed_time":0.9218644536,"remaining_time":0.6785946672},
{"learn":[8728.386718],"iteration":576,"passed_time":0.9232465445,"remaining_time":0.6768341219},
{"learn":[8726.912795],"iteration":577,"passed_time":0.9248526067,"remaining_time":0.6752384083},
{"learn":[8724.887465],"iteration":578,"passed_time":0.9264832213,"remaining_time":0.6736605115},
{"learn":[8722.682567],"iteration":579,"passed_time":0.928899972,"remaining_time":0.6726517039},
{"learn":[8721.043269],"iteration":580,"passed_time":0.930888794,"remaining_time":0.6713294401},
{"learn":[8716.334726],"iteration":581,"passed_time":0.9328522872,"remaining_time":0.6699866942},
{"learn":[8713.978513],"iteration":582,"passed_time":0.9348084988,"remaining_time":0.6686366107},
{"learn":[8712.136574],"iteration":583,"passed_time":0.9367805395,"remaining_time":0.6672957268},
{"learn":[8710.371467],"iteration":584,"passed_time":0.9382748893,"remaining_time":0.6656138104},
{"learn":[8709.14418],"iteration":585,"passed_time":0.9396217401,"remaining_time":0.6638283283},
{"learn":[8706.083006],"iteration":586,"passed_time":0.9413550807,"remaining_time":0.6623162663},
{"learn":[8703.207595],"iteration":587,"passed_time":0.9433076606,"remaining_time":0.6609570683},
{"learn":[8701.512635],"iteration":588,"passed_time":0.9453276707,"remaining_time":0.6596429078},
{"learn":[8699.50894],"iteration":589,"passed_time":0.9468655961,"remaining_time":0.6579913465},
{"learn":[8697.704692],"iteration":590,"passed_time":0.9485471869,"remaining_time":0.656439593},
{"learn":[8696.068883],"iteration":591,"passed_time":0.9501733285,"remaining_time":0.6548491859},
{"learn":[8695.129068],"iteration":592,"passed_time":0.9520123422,"remaining_time":0.653404761},
{"learn":[8691.847107],"iteration":593,"passed_time":0.9540091883,"remaining_time":0.6520668863},
{"learn":[8690.714463],"iteration":594,"passed_time":0.9554871134,"remaining_time":0.6503735814},
{"learn":[8688.918455],"iteration":595,"passed_time":0.9571840924,"remaining_time":0.6488294854},
{"learn":[8686.24159],"iteration":596,"passed_time":0.9595234547,"remaining_time":0.647718513},
{"learn":[8683.712708],"iteration":597,"passed_time":0.9614155538,"remaining_time":0.6463027636},
{"learn":[8680.099438],"iteration":598,"passed_time":0.9632896793,"remaining_time":0.6448733913},
{"learn":[8676.726131],"iteration":599,"passed_time":0.9648097062,"remaining_time":0.6432064708},
{"learn":[8675.563694],"iteration":600,"passed_time":0.9666745726,"remaining_time":0.6417689758},
{"learn":[8673.117632],"iteration":601,"passed_time":0.9681342267,"remaining_time":0.6400621632},
{"learn":[8670.897797],"iteration":602,"passed_time":0.9693717015,"remaining_time":0.6382098931},
{"learn":[8668.117958],"iteration":603,"passed_time":0.9705605246,"remaining_time":0.6363277612},
{"learn":[8666.031659],"iteration":604,"passed_time":0.9723044008,"remaining_time":0.6348103112},
{"learn":[8662.329486],"iteration":605,"passed_time":0.9741631382,"remaining_time":0.6333667928},
{"learn":[8661.114304],"iteration":606,"passed_time":0.9757207233,"remaining_time":0.6317269263},
{"learn":[8659.747477],"iteration":607,"passed_time":0.9772711198,"remaining_time":0.6300826957},
{"learn":[8656.480251],"iteration":608,"passed_time":0.9788395777,"remaining_time":0.6284503693},
{"learn":[8654.539406],"iteration":609,"passed_time":0.9803803505,"remaining_time":0.626800552},
{"learn":[8650.168176],"iteration":610,"passed_time":0.9827591431,"remaining_time":0.6256846263},
{"learn":[8647.97473],"iteration":611,"passed_time":0.9841057803,"remaining_time":0.6239102006},
{"learn":[8646.416575],"iteration":612,"passed_time":0.9853906365,"remaining_time":0.6220981669},
{"learn":[8645.716206],"iteration":613,"passed_time":0.9866740041,"remaining_time":0.6202869147},
{"learn":[8644.532514],"iteration":614,"passed_time":0.9883614479,"remaining_time":0.6187303373},
{"learn":[8642.935475],"iteration":615,"passed_time":0.9902910003,"remaining_time":0.6173242599},
{"learn":[8640.834704],"iteration":616,"passed_time":0.9918551445,"remaining_time":0.6156896602},
{"learn":[8638.147375],"iteration":617,"passed_time":0.993167395,"remaining_time":0.6138995872},
{"learn":[8635.648328],"iteration":618,"passed_time":0.9944682934,"remaining_time":0.6121040707},
{"learn":[8633.64389],"iteration":619,"passed_time":0.9957322491,"remaining_time":0.6102875075},
{"learn":[8630.704555],"iteration":620,"passed_time":0.9970365172,"remaining_time":0.6084973269},
{"learn":[8626.667132],"iteration":621,"passed_time":0.9982974178,"remaining_time":0.6066823536},
{"learn":[8625.265839],"iteration":622,"passed_time":0.9996282585,"remaining_time":0.6049114823},
{"learn":[8624.214864],"iteration":623,"passed_time":1.001323234,"remaining_time":0.6033614361},
{"learn":[8622.199558],"iteration":624,"passed_time":1.003823583,"remaining_time":0.6022941498},
{"learn":[8619.933775],"iteration":625,"passed_time":1.00584281,"remaining_time":0.600934842},
{"learn":[8618.474455],"iteration":626,"passed_time":1.007228735,"remaining_time":0.5991966797},
{"learn":[8617.074555],"iteration":627,"passed_time":1.008597132,"remaining_time":0.5974492563},
{"learn":[8615.537394],"iteration":628,"passed_time":1.009806918,"remaining_time":0.5956094859},
{"learn":[8613.237657],"iteration":629,"passed_time":1.011066653,"remaining_time":0.5938010503},
{"learn":[8611.096778],"iteration":630,"passed_time":1.012211606,"remaining_time":0.591927231},
{"learn":[8609.951489],"iteration":631,"passed_time":1.013349926,"remaining_time":0.5900518557},
{"learn":[8605.331405],"iteration":632,"passed_time":1.0146812,"remaining_time":0.5882906798},
{"learn":[8601.920987],"iteration":633,"passed_time":1.015890405,"remaining_time":0.5864603915},
{"learn":[8598.776858],"iteration":634,"passed_time":1.017175565,"remaining_time":0.5846757182},
{"learn":[8597.11809],"iteration":635,"passed_time":1.018796172,"remaining_time":0.5830846014},
{"learn":[8593.038924],"iteration":636,"passed_time":1.020454704,"remaining_time":0.5815150038},
{"learn":[8592.08316],"iteration":637,"passed_time":1.022042232,"remaining_time":0.5799048398},
{"learn":[8588.970599],"iteration":638,"passed_time":1.023705013,"remaining_time":0.5783372608},
{"learn":[8584.337713],"iteration":639,"passed_time":1.025440276,"remaining_time":0.5768101552},
{"learn":[8582.550159],"iteration":640,"passed_time":1.027013767,"remaining_time":0.575191798},
{"learn":[8580.660806],"iteration":641,"passed_time":1.028684328,"remaining_time":0.5736277095},
{"learn":[8578.572281],"iteration":642,"passed_time":1.030256255,"remaining_time":0.5720085271},
{"learn":[8576.453574],"iteration":643,"passed_time":1.031830584,"remaining_time":0.5703908198},
{"learn":[8573.781587],"iteration":644,"passed_time":1.033449428,"remaining_time":0.568797747},
{"learn":[8570.031503],"iteration":645,"passed_time":1.03653387,"remaining_time":0.5680077246},
{"learn":[8568.298793],"iteration":646,"passed_time":1.038559459,"remaining_time":0.5666329043},
{"learn":[8565.163777],"iteration":647,"passed_time":1.04041461,"remaining_time":0.5651634918},
{"learn":[8561.38111],"iteration":648,"passed_time":1.041982428,"remaining_time":0.5635374919},
{"learn":[8557.751696],"iteration":649,"passed_time":1.043516701,"remaining_time":0.561893608},
{"learn":[8555.164272],"iteration":650,"passed_time":1.045012077,"remaining_time":0.5602292089},
{"learn":[8554.050406],"iteration":651,"passed_time":1.046698106,"remaining_time":0.5586670875},
{"learn":[8552.631813],"iteration":652,"passed_time":1.04854413,"remaining_time":0.5571896068},
{"learn":[8550.650297],"iteration":653,"passed_time":1.050123993,"remaining_time":0.5555701858},
{"learn":[8548.427697],"iteration":654,"passed_time":1.05225999,"remaining_time":0.5542438116},
{"learn":[8546.951547],"iteration":655,"passed_time":1.053985877,"remaining_time":0.552699911},
{"learn":[8545.022989],"iteration":656,"passed_time":1.055620592,"remaining_time":0.5511078586},
{"learn":[8542.160079],"iteration":657,"passed_time":1.056997631,"remaining_time":0.5493817473},
{"learn":[8539.288786],"iteration":658,"passed_time":1.058525959,"remaining_time":0.5477349805},
{"learn":[8536.320809],"iteration":659,"passed_time":1.060025357,"remaining_time":0.5460736686},
{"learn":[8535.363895],"iteration":660,"passed_time":1.061287433,"remaining_time":0.5442911345},
{"learn":[8533.187597],"iteration":661,"passed_time":1.06274805,"remaining_time":0.5426115422},
{"learn":[8531.360617],"iteration":662,"passed_time":1.064689844,"remaining_time":0.5411771906},
{"learn":[8529.839804],"iteration":663,"passed_time":1.066745,"remaining_time":0.5397986749},
{"learn":[8527.933431],"iteration":664,"passed_time":1.068738716,"remaining_time":0.5383871726},
{"learn":[8526.202963],"iteration":665,"passed_time":1.070435389,"remaining_time":0.5368249548},
{"learn":[8523.651904],"iteration":666,"passed_time":1.071960699,"remaining_time":0.5351767805},
{"learn":[8522.039854],"iteration":667,"passed_time":1.073781277,"remaining_time":0.5336757246},
{"learn":[8520.054328],"iteration":668,"passed_time":1.076622449,"remaining_time":0.5326786705},
{"learn":[8515.678003],"iteration":669,"passed_time":1.078137887,"remaining_time":0.5310231381},
{"learn":[8513.14954],"iteration":670,"passed_time":1.079943351,"remaining_time":0.5295102275},
{"learn":[8510.889172],"iteration":671,"passed_time":1.082249315,"remaining_time":0.528240737},
{"learn":[8508.58477],"iteration":672,"passed_time":1.084499282,"remaining_time":0.5269409586},
{"learn":[8507.037962],"iteration":673,"passed_time":1.086662721,"remaining_time":0.5255965088},
{"learn":[8504.077459],"iteration":674,"passed_time":1.088291125,"remaining_time":0.5239920232},
{"learn":[8501.23693],"iteration":675,"passed_time":1.089714434,"remaining_time":0.5222891664},
{"learn":[8498.70234],"iteration":676,"passed_time":1.09173686,"remaining_time":0.5208729774},
{"learn":[8495.081851],"iteration":677,"passed_time":1.093263815,"remaining_time":0.5192196878},
{"learn":[8493.431209],"iteration":678,"passed_time":1.095282658,"remaining_time":0.5177993124},
{"learn":[8491.691477],"iteration":679,"passed_time":1.097828748,"remaining_time":0.5166252934},
{"learn":[8490.659683],"iteration":680,"passed_time":1.099719601,"remaining_time":0.5151403123},
{"learn":[8488.137597],"iteration":681,"passed_time":1.101471895,"remaining_time":0.5135895345},
{"learn":[8485.764275],"iteration":682,"passed_time":1.103380878,"remaining_time":0.5121108909},
{"learn":[8482.727773],"iteration":683,"passed_time":1.10554805,"remaining_time":0.5107502687},
{"learn":[8480.954605],"iteration":684,"passed_time":1.107236633,"remaining_time":0.5091672106},
{"learn":[8478.069459],"iteration":685,"passed_time":1.109240089,"remaining_time":0.507727971},
{"learn":[8476.868128],"iteration":686,"passed_time":1.111263883,"remaining_time":0.5062963541},
{"learn":[8474.893063],"iteration":687,"passed_time":1.11331705,"remaining_time":0.5048763368},
{"learn":[8472.138234],"iteration":688,"passed_time":1.116046028,"remaining_time":0.5037595279},
{"learn":[8469.587753],"iteration":689,"passed_time":1.118428652,"remaining_time":0.5024824379},
{"learn":[8467.285715],"iteration":690,"passed_time":1.120488676,"remaining_time":0.5010578886},
{"learn":[8465.074078],"iteration":691,"passed_time":1.122403652,"remaining_time":0.4995669436},
{"learn":[8461.634767],"iteration":692,"passed_time":1.124404038,"remaining_time":0.4981126113},
{"learn":[8459.385555],"iteration":693,"passed_time":1.127337585,"remaining_time":0.497068157},
{"learn":[8456.674221],"iteration":694,"passed_time":1.129311964,"remaining_time":0.4955973367},
{"learn":[8454.325393],"iteration":695,"passed_time":1.130836959,"remaining_time":0.4939287867},
{"learn":[8451.952481],"iteration":696,"passed_time":1.132482911,"remaining_time":0.4923132311},
{"learn":[8449.743289],"iteration":697,"passed_time":1.133922345,"remaining_time":0.4906082353},
{"learn":[8447.429461],"iteration":698,"passed_time":1.135340726,"remaining_time":0.4888949337},
{"learn":[8445.042547],"iteration":699,"passed_time":1.137786802,"remaining_time":0.4876229149},
{"learn":[8442.565045],"iteration":700,"passed_time":1.139678053,"remaining_time":0.4861108957},
{"learn":[8440.783698],"iteration":701,"passed_time":1.142104637,"remaining_time":0.4848250453},
{"learn":[8438.167435],"iteration":702,"passed_time":1.144766746,"remaining_time":0.4836354532},
{"learn":[8435.925874],"iteration":703,"passed_time":1.146672025,"remaining_time":0.482123465},
{"learn":[8433.262547],"iteration":704,"passed_time":1.148342568,"remaining_time":0.4805121383},
{"learn":[8431.056065],"iteration":705,"passed_time":1.150007636,"remaining_time":0.4788983641},
{"learn":[8428.233672],"iteration":706,"passed_time":1.151730996,"remaining_time":0.4773086025},
{"learn":[8426.454682],"iteration":707,"passed_time":1.153092849,"remaining_time":0.4755693671},
{"learn":[8424.338331],"iteration":708,"passed_time":1.15473344,"remaining_time":0.4739456007},
{"learn":[8421.807817],"iteration":709,"passed_time":1.156838807,"remaining_time":0.4725116256},
{"learn":[8419.829366],"iteration":710,"passed_time":1.159320273,"remaining_time":0.4712286343},
{"learn":[8417.250156],"iteration":711,"passed_time":1.161054617,"remaining_time":0.4696400696},
{"learn":[8414.652351],"iteration":712,"passed_time":1.16284688,"remaining_time":0.4680744102},
{"learn":[8412.743449],"iteration":713,"passed_time":1.164454105,"remaining_time":0.4664339972},
{"learn":[8411.477612],"iteration":714,"passed_time":1.166129686,"remaining_time":0.4648209239},
{"learn":[8410.218722],"iteration":715,"passed_time":1.167612832,"remaining_time":0.4631313468},
{"learn":[8408.840551],"iteration":716,"passed_time":1.169259869,"remaining_time":0.4615070334},
{"learn":[8408.033862],"iteration":717,"passed_time":1.171196457,"remaining_time":0.4599963801},
{"learn":[8404.703832],"iteration":718,"passed_time":1.173461202,"remaining_time":0.4586127925},
{"learn":[8402.361145],"iteration":719,"passed_time":1.175177278,"remaining_time":0.4570133858},
{"learn":[8399.549771],"iteration":720,"passed_time":1.176636501,"remaining_time":0.4553142632},
{"learn":[8395.911762],"iteration":721,"passed_time":1.178116876,"remaining_time":0.4536239496},
{"learn":[8393.608937],"iteration":722,"passed_time":1.179412135,"remaining_time":0.4518632939},
{"learn":[8391.686206],"iteration":723,"passed_time":1.180790289,"remaining_time":0.4501355246},
{"learn":[8390.137041],"iteration":724,"passed_time":1.182204858,"remaining_time":0.4484225324},
{"learn":[8389.113012],"iteration":725,"passed_time":1.183493097,"remaining_time":0.4466626841},
{"learn":[8387.212626],"iteration":726,"passed_time":1.186144413,"remaining_time":0.44541599},
{"learn":[8385.395083],"iteration":727,"passed_time":1.188371625,"remaining_time":0.4440069806},
{"learn":[8384.505209],"iteration":728,"passed_time":1.190193293,"remaining_time":0.4424449692},
{"learn":[8381.656836],"iteration":729,"passed_time":1.192119794,"remaining_time":0.4409210198},
{"learn":[8377.732111],"iteration":730,"passed_time":1.193615753,"remaining_time":0.4392375344},
{"learn":[8376.097621],"iteration":731,"passed_time":1.195150979,"remaining_time":0.4375689375},
{"learn":[8372.936084],"iteration":732,"passed_time":1.196729243,"remaining_time":0.4359163818},
{"learn":[8370.147944],"iteration":733,"passed_time":1.198743535,"remaining_time":0.4344220442},
{"learn":[8367.054638],"iteration":734,"passed_time":1.200866803,"remaining_time":0.4329655819},
{"learn":[8364.629707],"iteration":735,"passed_time":1.203030835,"remaining_time":0.43152193},
{"learn":[8363.516571],"iteration":736,"passed_time":1.204881293,"remaining_time":0.4299644236},
{"learn":[8360.585556],"iteration":737,"passed_time":1.206751144,"remaining_time":0.4284130076},
{"learn":[8358.414037],"iteration":738,"passed_time":1.208344775,"remaining_time":0.4267631749},
{"learn":[8356.215372],"iteration":739,"passed_time":1.210092511,"remaining_time":0.4251676389},
{"learn":[8355.199724],"iteration":740,"passed_time":1.212121735,"remaining_time":0.4236700801},
{"learn":[8351.737166],"iteration":741,"passed_time":1.213819777,"remaining_time":0.4220559331},
{"learn":[8348.682825],"iteration":742,"passed_time":1.215835524,"remaining_time":0.4205514531},
{"learn":[8347.369807],"iteration":743,"passed_time":1.218258873,"remaining_time":0.4191858488},
{"learn":[8345.018451],"iteration":744,"passed_time":1.220356515,"remaining_time":0.4177059211},
{"learn":[8343.783162],"iteration":745,"passed_time":1.222302081,"remaining_time":0.4161725583},
{"learn":[8342.526003],"iteration":746,"passed_time":1.224302845,"remaining_time":0.414656787},
{"learn":[8341.500874],"iteration":747,"passed_time":1.226059147,"remaining_time":0.4130573599},
{"learn":[8340.23611],"iteration":748,"passed_time":1.228146804,"remaining_time":0.4115685551},
{"learn":[8337.016869],"iteration":749,"passed_time":1.230055827,"remaining_time":0.4100186088},
{"learn":[8335.594715],"iteration":750,"passed_time":1.232222034,"remaining_time":0.4085529781},
{"learn":[8333.183837],"iteration":751,"passed_time":1.234774861,"remaining_time":0.4072129861},
{"learn":[8329.98119],"iteration":752,"passed_time":1.236668446,"remaining_time":0.4056535274},
{"learn":[8327.309467],"iteration":753,"passed_time":1.238430996,"remaining_time":0.404050431},
{"learn":[8324.797498],"iteration":754,"passed_time":1.240324658,"remaining_time":0.4024894584},
{"learn":[8322.608361],"iteration":755,"passed_time":1.242277428,"remaining_time":0.400946683},
{"learn":[8321.19773],"iteration":756,"passed_time":1.244073618,"remaining_time":0.3993525616},
{"learn":[8318.776626],"iteration":757,"passed_time":1.245828472,"remaining_time":0.3977447101},
{"learn":[8317.626099],"iteration":758,"passed_time":1.248472754,"remaining_time":0.3964188851},
{"learn":[8316.111739],"iteration":759,"passed_time":1.250270494,"remaining_time":0.3948222613},
{"learn":[8315.189574],"iteration":760,"passed_time":1.252111732,"remaining_time":0.3932387698},
{"learn":[8314.065332],"iteration":761,"passed_time":1.253708455,"remaining_time":0.3915782312},
{"learn":[8311.911194],"iteration":762,"passed_time":1.255327545,"remaining_time":0.3899248075},
{"learn":[8310.301349],"iteration":763,"passed_time":1.256835363,"remaining_time":0.3882371015},
{"learn":[8307.306432],"iteration":764,"passed_time":1.258602996,"remaining_time":0.3866296785},
{"learn":[8304.228633],"iteration":765,"passed_time":1.260943013,"remaining_time":0.3851966905},
{"learn":[8301.220442],"iteration":766,"passed_time":1.262915983,"remaining_time":0.3836498357},
{"learn":[8299.383833],"iteration":767,"passed_time":1.265276192,"remaining_time":0.3822188498},
{"learn":[8296.467843],"iteration":768,"passed_time":1.267453942,"remaining_time":0.3807306381},
{"learn":[8293.254907],"iteration":769,"passed_time":1.269238805,"remaining_time":0.3791232795},
{"learn":[8290.722389],"iteration":770,"passed_time":1.271137932,"remaining_time":0.3775493986},
{"learn":[8289.104504],"iteration":771,"passed_time":1.27287545,"remaining_time":0.3759269464},
{"learn":[8285.041919],"iteration":772,"passed_time":1.274858514,"remaining_time":0.3743763036},
{"learn":[8284.301463],"iteration":773,"passed_time":1.276677499,"remaining_time":0.3727766342},
{"learn":[8282.914467],"iteration":774,"passed_time":1.279110501,"remaining_time":0.3713546614},
{"learn":[8282.028031],"iteration":775,"passed_time":1.281118079,"remaining_time":0.3698072805},
{"learn":[8279.866956],"iteration":776,"passed_time":1.282905924,"remaining_time":0.3681956514},
{"learn":[8277.351822],"iteration":777,"passed_time":1.284513387,"remaining_time":0.3665320977},
{"learn":[8275.895215],"iteration":778,"passed_time":1.286346587,"remaining_time":0.3649327287},
{"learn":[8272.982809],"iteration":779,"passed_time":1.288055054,"remaining_time":0.3632975793},
{"learn":[8271.121056],"iteration":780,"passed_time":1.289505882,"remaining_time":0.3615899978},
{"learn":[8270.29195],"iteration":781,"passed_time":1.291204322,"remaining_time":0.3599521},
{"learn":[8267.5305],"iteration":782,"passed_time":1.293341544,"remaining_time":0.3584356514},
{"learn":[8264.176047],"iteration":783,"passed_time":1.295249816,"remaining_time":0.3568545412},
{"learn":[8262.653913],"iteration":784,"passed_time":1.296892377,"remaining_time":0.355199823},
{"learn":[8261.121941],"iteration":785,"passed_time":1.298762582,"remaining_time":0.3536071153},
{"learn":[8258.481036],"iteration":786,"passed_time":1.300524276,"remaining_time":0.351984334},
{"learn":[8257.177503],"iteration":787,"passed_time":1.30208741,"remaining_time":0.3503077804},
{"learn":[8254.584479],"iteration":788,"passed_time":1.303467161,"remaining_time":0.3485824728},
{"learn":[8250.917905],"iteration":789,"passed_time":1.304793077,"remaining_time":0.3468437295},
{"learn":[8249.246764],"iteration":790,"passed_time":1.306449656,"remaining_time":0.3451933983},
{"learn":[8246.575408],"iteration":791,"passed_time":1.308824999,"remaining_time":0.3437318178},
{"learn":[8245.628798],"iteration":792,"passed_time":1.310597711,"remaining_time":0.3421106256},
{"learn":[8244.067587],"iteration":793,"passed_time":1.312321314,"remaining_time":0.3404763107},
{"learn":[8241.395112],"iteration":794,"passed_time":1.313839439,"remaining_time":0.3387887863},
{"learn":[8238.719077],"iteration":795,"passed_time":1.31532542,"remaining_time":0.3370934492},
{"learn":[8236.23327],"iteration":796,"passed_time":1.317494937,"remaining_time":0.335572738},
{"learn":[8234.95521],"iteration":797,"passed_time":1.31949422,"remaining_time":0.3340073089},
{"learn":[8233.893454],"iteration":798,"passed_time":1.321274725,"remaining_time":0.3323857567},
{"learn":[8231.876407],"iteration":799,"passed_time":1.323744265,"remaining_time":0.3309360662},
{"learn":[8230.050596],"iteration":800,"passed_time":1.325650636,"remaining_time":0.3293439157},
{"learn":[8228.693078],"iteration":801,"passed_time":1.327253402,"remaining_time":0.327676027},
{"learn":[8225.862774],"iteration":802,"passed_time":1.32890378,"remaining_time":0.326019981},
{"learn":[8223.210113],"iteration":803,"passed_time":1.330422237,"remaining_time":0.324331789},
{"learn":[8220.782613],"iteration":804,"passed_time":1.332011704,"remaining_time":0.3226612202},
{"learn":[8219.617242],"iteration":805,"passed_time":1.333470385,"remaining_time":0.3209593731},
{"learn":[8215.086736],"iteration":806,"passed_time":1.335030597,"remaining_time":0.3192824105},
{"learn":[8213.443186],"iteration":807,"passed_time":1.336677958,"remaining_time":0.3176264455},
{"learn":[8211.299911],"iteration":808,"passed_time":1.33909075,"remaining_time":0.3161512154},
{"learn":[8209.705201],"iteration":809,"passed_time":1.341180922,"remaining_time":0.3145979941},
{"learn":[8208.573266],"iteration":810,"passed_time":1.34269176,"remaining_time":0.3129084374},
{"learn":[8205.403218],"iteration":811,"passed_time":1.344141111,"remaining_time":0.3112050849},
{"learn":[8203.665005],"iteration":812,"passed_time":1.34580041,"remaining_time":0.3095506479},
{"learn":[8200.558541],"iteration":813,"passed_time":1.347304838,"remaining_time":0.3078608106},
{"learn":[8197.546077],"iteration":814,"passed_time":1.349303315,"remaining_time":0.3062835746},
{"learn":[8195.146503],"iteration":815,"passed_time":1.350847897,"remaining_time":0.3046029571},
{"learn":[8191.634774],"iteration":816,"passed_time":1.352982713,"remaining_time":0.3030548794},
{"learn":[8190.516371],"iteration":817,"passed_time":1.355016889,"remaining_time":0.3014829752},
{"learn":[8187.559562],"iteration":818,"passed_time":1.356816961,"remaining_time":0.299858205},
{"learn":[8184.923543],"iteration":819,"passed_time":1.358363987,"remaining_time":0.2981774605},
{"learn":[8181.69695],"iteration":820,"passed_time":1.35970573,"remaining_time":0.2964522847},
{"learn":[8180.05302],"iteration":821,"passed_time":1.361572021,"remaining_time":0.2948416298},
{"learn":[8177.346748],"iteration":822,"passed_time":1.36296241,"remaining_time":0.2931280032},
{"learn":[8175.597122],"iteration":823,"passed_time":1.364301697,"remaining_time":0.2914042459},
{"learn":[8173.311527],"iteration":824,"passed_time":1.365783251,"remaining_time":0.2897115988},
{"learn":[8171.01132],"iteration":825,"passed_time":1.367915434,"remaining_time":0.2881565199},
{"learn":[8168.72004],"iteration":826,"passed_time":1.370216037,"remaining_time":0.2866352774},
{"learn":[8167.608469],"iteration":827,"passed_time":1.372017,"remaining_time":0.2850083624},
{"learn":[8164.564427],"iteration":828,"passed_time":1.373572601,"remaining_time":0.2833304159},
{"learn":[8161.356767],"iteration":829,"passed_time":1.375214803,"remaining_time":0.2816705018},
{"learn":[8159.959513],"iteration":830,"passed_time":1.377011718,"remaining_time":0.2800420943},
{"learn":[8157.488798],"iteration":831,"passed_time":1.378607123,"remaining_time":0.2783725922},
{"learn":[8155.511486],"iteration":832,"passed_time":1.380030725,"remaining_time":0.2766688248},
{"learn":[8154.009793],"iteration":833,"passed_time":1.38139892,"remaining_time":0.2749547011},
{"learn":[8152.038972],"iteration":834,"passed_time":1.383563508,"remaining_time":0.2733987771},
{"learn":[8148.744509],"iteration":835,"passed_time":1.385936553,"remaining_time":0.2718822902},
{"learn":[8146.825891],"iteration":836,"passed_time":1.387618174,"remaining_time":0.2702291067},
{"learn":[8144.800565],"iteration":837,"passed_time":1.389257772,"remaining_time":0.2685677317},
{"learn":[8142.709403],"iteration":838,"passed_time":1.39137174,"remaining_time":0.2669974376},
{"learn":[8141.154096],"iteration":839,"passed_time":1.393204682,"remaining_time":0.2653723203},
{"learn":[8136.961516],"iteration":840,"passed_time":1.394701314,"remaining_time":0.263683126},
{"learn":[8134.51601],"iteration":841,"passed_time":1.396019222,"remaining_time":0.2619608517},
{"learn":[8133.669763],"iteration":842,"passed_time":1.397554726,"remaining_time":0.2602800617},
{"learn":[8131.583761],"iteration":843,"passed_time":1.400113053,"remaining_time":0.2587886685},
{"learn":[8130.580777],"iteration":844,"passed_time":1.401986239,"remaining_time":0.2571690735},
{"learn":[8126.741395],"iteration":845,"passed_time":1.403423166,"remaining_time":0.2554694653},
{"learn":[8124.057238],"iteration":846,"passed_time":1.405290735,"remaining_time":0.2538482673},
{"learn":[8121.208065],"iteration":847,"passed_time":1.407134232,"remaining_time":0.2522221736},
{"learn":[8118.905891],"iteration":848,"passed_time":1.408824719,"remaining_time":0.250568354},
{"learn":[8116.554236],"iteration":849,"passed_time":1.41082192,"remaining_time":0.2489685742},
{"learn":[8114.589566],"iteration":850,"passed_time":1.412651819,"remaining_time":0.2473385676},
{"learn":[8113.232895],"iteration":851,"passed_time":1.4147355,"remaining_time":0.2457521761},
{"learn":[8110.859279],"iteration":852,"passed_time":1.41648787,"remaining_time":0.2441075228},
{"learn":[8108.453626],"iteration":853,"passed_time":1.418014044,"remaining_time":0.2424239466},
{"learn":[8107.411278],"iteration":854,"passed_time":1.419450763,"remaining_time":0.2407255679},
{"learn":[8105.235854],"iteration":855,"passed_time":1.420942737,"remaining_time":0.239037096},
{"learn":[8102.167362],"iteration":856,"passed_time":1.422518062,"remaining_time":0.2373629905},
{"learn":[8100.646719],"iteration":857,"passed_time":1.424188852,"remaining_time":0.235704915},
{"learn":[8099.058425],"iteration":858,"passed_time":1.425654921,"remaining_time":0.234013206},
{"learn":[8097.223121],"iteration":859,"passed_time":1.427100953,"remaining_time":0.2323187599},
{"learn":[8095.526935],"iteration":860,"passed_time":1.429225651,"remaining_time":0.2307344548},
{"learn":[8094.572545],"iteration":861,"passed_time":1.431448964,"remaining_time":0.2291646833},
{"learn":[8092.683428],"iteration":862,"passed_time":1.433022603,"remaining_time":0.2274902626},
{"learn":[8090.008661],"iteration":863,"passed_time":1.434426539,"remaining_time":0.2257893625},
{"learn":[8089.226708],"iteration":864,"passed_time":1.435977695,"remaining_time":0.2241121258},
{"learn":[8085.924579],"iteration":865,"passed_time":1.437823718,"remaining_time":0.2224808062},
{"learn":[8082.492836],"iteration":866,"passed_time":1.439234854,"remaining_time":0.2207822787},
{"learn":[8080.119454],"iteration":867,"passed_time":1.440529523,"remaining_time":0.2190667016},
{"learn":[8077.179101],"iteration":868,"passed_time":1.441891869,"remaining_time":0.2173622955},
{"learn":[8076.461055],"iteration":869,"passed_time":1.443309519,"remaining_time":0.2156669396},
{"learn":[8073.689496],"iteration":870,"passed_time":1.445548188,"remaining_time":0.2140938189},
{"learn":[8072.2862],"iteration":871,"passed_time":1.447443478,"remaining_time":0.2124687674},
{"learn":[8071.146989],"iteration":872,"passed_time":1.448873463,"remaining_time":0.2107754064},
{"learn":[8069.423696],"iteration":873,"passed_time":1.450350173,"remaining_time":0.2090893842},
{"learn":[8067.723364],"iteration":874,"passed_time":1.452001427,"remaining_time":0.2074287753},
{"learn":[8065.826582],"iteration":875,"passed_time":1.454150819,"remaining_time":0.2058387003},
{"learn":[8062.598509],"iteration":876,"passed_time":1.456120134,"remaining_time":0.2042220941},
{"learn":[8059.998612],"iteration":877,"passed_time":1.457426698,"remaining_time":0.2025125936},
{"learn":[8057.717228],"iteration":878,"passed_time":1.459472351,"remaining_time":0.2009057502},
{"learn":[8055.714782],"iteration":879,"passed_time":1.461518138,"remaining_time":0.1992979279},
{"learn":[8054.223935],"iteration":880,"passed_time":1.463559235,"remaining_time":0.1976884779},
{"learn":[8051.593797],"iteration":881,"passed_time":1.465217734,"remaining_time":0.1960268624},
{"learn":[8049.158838],"iteration":882,"passed_time":1.466855625,"remaining_time":0.1943625234},
{"learn":[8046.359549],"iteration":883,"passed_time":1.468486912,"remaining_time":0.1926973776},
{"learn":[8043.891284],"iteration":884,"passed_time":1.470398837,"remaining_time":0.1910687754},
{"learn":[8043.464363],"iteration":885,"passed_time":1.472215095,"remaining_time":0.1894272244},
{"learn":[8042.070412],"iteration":886,"passed_time":1.474899551,"remaining_time":0.1878958842},
{"learn":[8039.913168],"iteration":887,"passed_time":1.477856639,"remaining_time":0.1863963329},
{"learn":[8036.144912],"iteration":888,"passed_time":1.479782859,"remaining_time":0.184764789},
{"learn":[8034.247138],"iteration":889,"passed_time":1.481491943,"remaining_time":0.1831057458},
{"learn":[8033.340448],"iteration":890,"passed_time":1.483258949,"remaining_time":0.1814536761},
{"learn":[8031.09178],"iteration":891,"passed_time":1.485081326,"remaining_time":0.1798080529},
{"learn":[8030.758519],"iteration":892,"passed_time":1.486443223,"remaining_time":0.1781068588},
{"learn":[8029.835347],"iteration":893,"passed_time":1.488131078,"remaining_time":0.1764450719},
{"learn":[8029.105072],"iteration":894,"passed_time":1.490166166,"remaining_time":0.1748239636},
{"learn":[8027.509648],"iteration":895,"passed_time":1.492120282,"remaining_time":0.1731925327},
{"learn":[8025.034211],"iteration":896,"passed_time":1.493724626,"remaining_time":0.171520219},
{"learn":[8023.231256],"iteration":897,"passed_time":1.495655998,"remaining_time":0.1698852025},
{"learn":[8021.792331],"iteration":898,"passed_time":1.49749736,"remaining_time":0.1682394142},
{"learn":[8020.845702],"iteration":899,"passed_time":1.499155947,"remaining_time":0.166572883},
{"learn":[8018.907811],"iteration":900,"passed_time":1.500576149,"remaining_time":0.1648801762},
{"learn":[8016.667954],"iteration":901,"passed_time":1.502518348,"remaining_time":0.1632447873},
{"learn":[8014.406227],"iteration":902,"passed_time":1.50495324,"remaining_time":0.1616616438},
{"learn":[8013.106828],"iteration":903,"passed_time":1.507292641,"remaining_time":0.1600664752},
{"learn":[8010.687139],"iteration":904,"passed_time":1.509113919,"remaining_time":0.1584152733},
{"learn":[8009.716467],"iteration":905,"passed_time":1.510581689,"remaining_time":0.1567270185},
{"learn":[8008.376823],"iteration":906,"passed_time":1.512147084,"remaining_time":0.15504926},
{"learn":[8008.131592],"iteration":907,"passed_time":1.513833449,"remaining_time":0.1533840058},
{"learn":[8006.192669],"iteration":908,"passed_time":1.515286533,"remaining_time":0.1516953515},
{"learn":[8005.160538],"iteration":909,"passed_time":1.516699595,"remaining_time":0.1500032567},
{"learn":[8003.383695],"iteration":910,"passed_time":1.518040712,"remaining_time":0.1483047457},
{"learn":[8000.362019],"iteration":911,"passed_time":1.519804135,"remaining_time":0.1466477674},
{"learn":[7998.741401],"iteration":912,"passed_time":1.521834282,"remaining_time":0.1450159721},
{"learn":[7997.957757],"iteration":913,"passed_time":1.523612314,"remaining_time":0.1433595831},
{"learn":[7996.087728],"iteration":914,"passed_time":1.525304021,"remaining_time":0.1416949091},
{"learn":[7994.458444],"iteration":915,"passed_time":1.526917858,"remaining_time":0.1400230351},
{"learn":[7993.355607],"iteration":916,"passed_time":1.528595347,"remaining_time":0.1383570488},
{"learn":[7991.688789],"iteration":917,"passed_time":1.530023663,"remaining_time":0.1366687803},
{"learn":[7990.149288],"iteration":918,"passed_time":1.531591551,"remaining_time":0.1349933793},
{"learn":[7988.172872],"iteration":919,"passed_time":1.53299071,"remaining_time":0.13330354},
{"learn":[7987.130238],"iteration":920,"passed_time":1.53507123,"remaining_time":0.1316727765},
{"learn":[7986.17789],"iteration":921,"passed_time":1.537503672,"remaining_time":0.1300708096},
{"learn":[7985.114541],"iteration":922,"passed_time":1.539728832,"remaining_time":0.1284497509},
{"learn":[7981.168902],"iteration":923,"passed_time":1.541316362,"remaining_time":0.1267749388},
{"learn":[7979.626664],"iteration":924,"passed_time":1.543129948,"remaining_time":0.1251186444},
{"learn":[7978.222713],"iteration":925,"passed_time":1.544455536,"remaining_time":0.1234230126},
{"learn":[7974.744627],"iteration":926,"passed_time":1.546604407,"remaining_time":0.1217930116},
{"learn":[7972.868819],"iteration":927,"passed_time":1.548160808,"remaining_time":0.1201159248},
{"learn":[7970.852952],"iteration":928,"passed_time":1.550588636,"remaining_time":0.1185056977},
{"learn":[7969.633158],"iteration":929,"passed_time":1.552674916,"remaining_time":0.1168680045},
{"learn":[7966.489977],"iteration":930,"passed_time":1.554397525,"remaining_time":0.1152023944},
{"learn":[7964.710937],"iteration":931,"passed_time":1.556006439,"remaining_time":0.1135283668},
{"learn":[7962.589085],"iteration":932,"passed_time":1.557734372,"remaining_time":0.1118630256},
{"learn":[7960.528597],"iteration":933,"passed_time":1.559127624,"remaining_time":0.1101739006},
{"learn":[7958.173543],"iteration":934,"passed_time":1.560893163,"remaining_time":0.1085112894},
{"learn":[7956.975914],"iteration":935,"passed_time":1.562333497,"remaining_time":0.106826222},
{"learn":[7955.324014],"iteration":936,"passed_time":1.564351015,"remaining_time":0.1051804845},
{"learn":[7954.196321],"iteration":937,"passed_time":1.566363538,"remaining_time":0.1035336241},
{"learn":[7953.409729],"iteration":938,"passed_time":1.567994601,"remaining_time":0.1018612041},
{"learn":[7950.844256],"iteration":939,"passed_time":1.569524507,"remaining_time":0.1001824153},
{"learn":[7949.809775],"iteration":940,"passed_time":1.571825705,"remaining_time":0.09855230245},
{"learn":[7948.288549],"iteration":941,"passed_time":1.573890654,"remaining_time":0.0969062186},
{"learn":[7947.362872],"iteration":942,"passed_time":1.575301734,"remaining_time":0.09521972308},
{"learn":[7945.495803],"iteration":943,"passed_time":1.5766809,"remaining_time":0.0935319178},
{"learn":[7943.696734],"iteration":944,"passed_time":1.578060034,"remaining_time":0.09184476386},
{"learn":[7940.565625],"iteration":945,"passed_time":1.58000955,"remaining_time":0.09019081996},
{"learn":[7938.972616],"iteration":946,"passed_time":1.582769937,"remaining_time":0.08858163322},
{"learn":[7936.709509],"iteration":947,"passed_time":1.585333743,"remaining_time":0.08695923485},
{"learn":[7934.192419],"iteration":948,"passed_time":1.586881979,"remaining_time":0.08528027494},
{"learn":[7932.917483],"iteration":949,"passed_time":1.588577377,"remaining_time":0.08360933562},
{"learn":[7930.244578],"iteration":950,"passed_time":1.590243358,"remaining_time":0.0819368292},
{"learn":[7928.674814],"iteration":951,"passed_time":1.591960462,"remaining_time":0.08026691404},
{"learn":[7927.647766],"iteration":952,"passed_time":1.593545513,"remaining_time":0.07859038732},
{"learn":[7924.4654],"iteration":953,"passed_time":1.595262096,"remaining_time":0.07692039458},
{"learn":[7923.390928],"iteration":954,"passed_time":1.597309322,"remaining_time":0.0752658843},
{"learn":[7921.072648],"iteration":955,"passed_time":1.599329467,"remaining_time":0.07360930602},
{"learn":[7917.310915],"iteration":956,"passed_time":1.600908985,"remaining_time":0.07193216966},
{"learn":[7916.009623],"iteration":957,"passed_time":1.602241612,"remaining_time":0.07024441305},
{"learn":[7914.882774],"iteration":958,"passed_time":1.603732192,"remaining_time":0.06856415003},
{"learn":[7913.250216],"iteration":959,"passed_time":1.605129886,"remaining_time":0.06688041194},
{"learn":[7911.269021],"iteration":960,"passed_time":1.606856007,"remaining_time":0.06521059758},
{"learn":[7909.16559],"iteration":961,"passed_time":1.608269854,"remaining_time":0.06352833104},
{"learn":[7906.889181],"iteration":962,"passed_time":1.609634532,"remaining_time":0.06184473281},
{"learn":[7905.733723],"iteration":963,"passed_time":1.611843052,"remaining_time":0.060193309},
{"learn":[7905.163683],"iteration":964,"passed_time":1.614351604,"remaining_time":0.05855161256},
{"learn":[7904.00363],"iteration":965,"passed_time":1.615879093,"remaining_time":0.05687359128},
{"learn":[7901.641285],"iteration":966,"passed_time":1.617931153,"remaining_time":0.05521378288},
{"learn":[7899.301959],"iteration":967,"passed_time":1.619242104,"remaining_time":0.05352866459},
{"learn":[7898.363883],"iteration":968,"passed_time":1.620669014,"remaining_time":0.0518480283},
{"learn":[7897.767809],"iteration":969,"passed_time":1.621944521,"remaining_time":0.05016323261},
{"learn":[7895.830464],"iteration":970,"passed_time":1.623312114,"remaining_time":0.04848203017},
{"learn":[7894.209043],"iteration":971,"passed_time":1.624754476,"remaining_time":0.04680362688},
{"learn":[7893.402019],"iteration":972,"passed_time":1.626540518,"remaining_time":0.04513524562},
{"learn":[7892.844564],"iteration":973,"passed_time":1.628365865,"remaining_time":0.04346767197},
{"learn":[7891.642705],"iteration":974,"passed_time":1.6306034,"remaining_time":0.04181034359},
{"learn":[7888.787137],"iteration":975,"passed_time":1.632394562,"remaining_time":0.04014084988},
{"learn":[7885.879054],"iteration":976,"passed_time":1.634332743,"remaining_time":0.03847456817},
{"learn":[7884.170633],"iteration":977,"passed_time":1.63607967,"remaining_time":0.03680342815},
{"learn":[7881.855574],"iteration":978,"passed_time":1.638055711,"remaining_time":0.03513704794},
{"learn":[7880.242673],"iteration":979,"passed_time":1.639624954,"remaining_time":0.03346173376},
{"learn":[7879.351559],"iteration":980,"passed_time":1.641412175,"remaining_time":0.03179085763},
{"learn":[7878.195347],"iteration":981,"passed_time":1.643434473,"remaining_time":0.03012405349},
{"learn":[7875.540629],"iteration":982,"passed_time":1.645302551,"remaining_time":0.02845385897},
{"learn":[7874.263021],"iteration":983,"passed_time":1.646703031,"remaining_time":0.02677565903},
{"learn":[7872.457954],"iteration":984,"passed_time":1.648231146,"remaining_time":0.02509996669},
{"learn":[7869.584602],"iteration":985,"passed_time":1.649642883,"remaining_time":0.02342292126},
{"learn":[7869.203526],"iteration":986,"passed_time":1.651391723,"remaining_time":0.0217508535},
{"learn":[7868.593948],"iteration":987,"passed_time":1.653738985,"remaining_time":0.02008589861},
{"learn":[7866.279063],"iteration":988,"passed_time":1.656136235,"remaining_time":0.01842011991},
{"learn":[7863.60613],"iteration":989,"passed_time":1.658050535,"remaining_time":0.01674798521},
{"learn":[7860.668188],"iteration":990,"passed_time":1.659544857,"remaining_time":0.01507154764},
{"learn":[7859.160194],"iteration":991,"passed_time":1.661273939,"remaining_time":0.01339737048},
{"learn":[7857.508329],"iteration":992,"passed_time":1.662607711,"remaining_time":0.01172029605},
{"learn":[7855.253335],"iteration":993,"passed_time":1.663988671,"remaining_time":0.01004419721},
{"learn":[7854.164666],"iteration":994,"passed_time":1.665456523,"remaining_time":0.008369128255},
{"learn":[7853.179519],"iteration":995,"passed_time":1.667284107,"remaining_time":0.006695920108},
{"learn":[7850.644681],"iteration":996,"passed_time":1.669565591,"remaining_time":0.005023768078},
{"learn":[7848.099639],"iteration":997,"passed_time":1.671315962,"remaining_time":0.003349330585},
{"learn":[7846.40523],"iteration":998,"passed_time":1.672990901,"remaining_time":0.001674665567},
{"learn":[7844.671104],"iteration":999,"passed_time":1.674825034,"remaining_time":0}
]}